{
  "data": [
    {
      "Exclusive time %": 5.8e-05,
      "Inclusive time %": 5.8e-05,
      "exclusive_time_rank_avg": 0.000701,
      "exclusive_time_rank_max": 0.00077,
      "exclusive_time_rank_min": 0.000658,
      "inclusive_time_rank_avg": 0.000701,
      "inclusive_time_rank_max": 0.00077,
      "inclusive_time_rank_min": 0.000658
    },
    {
      "path": "main",
      "Exclusive time %": 0.000326,
      "Inclusive time %": 99.999942,
      "exclusive_time_rank_avg": 0.003952,
      "exclusive_time_rank_max": 0.004613,
      "exclusive_time_rank_min": 0.003552,
      "inclusive_time_rank_avg": 1212.543771,
      "inclusive_time_rank_max": 1212.545135,
      "inclusive_time_rank_min": 1212.541937
    },
    {
      "path": "main/load-model",
      "Exclusive time %": 0.068597,
      "Inclusive time %": 0.073997,
      "exclusive_time_rank_avg": 0.831769,
      "exclusive_time_rank_max": 0.895737,
      "exclusive_time_rank_min": 0.596566,
      "inclusive_time_rank_avg": 0.897246,
      "inclusive_time_rank_max": 0.897396,
      "inclusive_time_rank_min": 0.897061
    },
    {
      "path": "main/output-spike",
      "Exclusive time %": 0.00011,
      "Inclusive time %": 0.006382,
      "exclusive_time_rank_avg": 0.001331,
      "exclusive_time_rank_max": 0.001728,
      "exclusive_time_rank_min": 0.001055,
      "inclusive_time_rank_avg": 0.077381,
      "inclusive_time_rank_max": 0.078215,
      "inclusive_time_rank_min": 0.076479
    },
    {
      "path": "main/MPI_Allreduce",
      "Exclusive time %": 0.000245,
      "Inclusive time %": 0.000245,
      "exclusive_time_rank_avg": 0.002971,
      "exclusive_time_rank_max": 0.004376,
      "exclusive_time_rank_min": 0.001043,
      "inclusive_time_rank_avg": 0.002971,
      "inclusive_time_rank_max": 0.004376,
      "inclusive_time_rank_min": 0.001043
    },
    {
      "path": "main/load-model/MPI_Allreduce",
      "Exclusive time %": 0.0054,
      "Inclusive time %": 0.0054,
      "exclusive_time_rank_avg": 0.065477,
      "exclusive_time_rank_max": 0.300657,
      "exclusive_time_rank_min": 0.001506,
      "inclusive_time_rank_avg": 0.065477,
      "inclusive_time_rank_max": 0.300657,
      "inclusive_time_rank_min": 0.001506
    },
    {
      "path": "main/output-spike/MPI_Allreduce",
      "Exclusive time %": 1.4e-05,
      "Inclusive time %": 1.4e-05,
      "exclusive_time_rank_avg": 0.000164,
      "exclusive_time_rank_max": 0.000247,
      "exclusive_time_rank_min": 2.6e-05,
      "inclusive_time_rank_avg": 0.000164,
      "inclusive_time_rank_max": 0.000247,
      "inclusive_time_rank_min": 2.6e-05
    },
    {
      "path": "main/simulation",
      "Exclusive time %": 0.015086,
      "Inclusive time %": 99.915413,
      "exclusive_time_rank_avg": 0.182925,
      "exclusive_time_rank_max": 0.204418,
      "exclusive_time_rank_min": 0.16386,
      "inclusive_time_rank_avg": 1211.518815,
      "inclusive_time_rank_max": 1211.518836,
      "inclusive_time_rank_min": 1211.518796
    },
    {
      "path": "main/simulation/spike-exchange",
      "Exclusive time %": 0.023694,
      "Inclusive time %": 2.916982,
      "exclusive_time_rank_avg": 0.287295,
      "exclusive_time_rank_max": 0.320354,
      "exclusive_time_rank_min": 0.274635,
      "inclusive_time_rank_avg": 35.369699,
      "inclusive_time_rank_max": 88.405296,
      "inclusive_time_rank_min": 1.906226
    },
    {
      "path": "main/simulation/spike-exchange/spike-exchange",
      "Exclusive time %": 0.000262,
      "Inclusive time %": 2.893288,
      "exclusive_time_rank_avg": 0.003176,
      "exclusive_time_rank_max": 0.004424,
      "exclusive_time_rank_min": 0.002407,
      "inclusive_time_rank_avg": 35.082403,
      "inclusive_time_rank_max": 88.130229,
      "inclusive_time_rank_min": 1.585872
    },
    {
      "path": "main/simulation/spike-exchange/spike-exchange/imbalance",
      "Exclusive time %": 0.000368,
      "Inclusive time %": 2.886348,
      "exclusive_time_rank_avg": 0.004461,
      "exclusive_time_rank_max": 0.008602,
      "exclusive_time_rank_min": 0.002215,
      "inclusive_time_rank_avg": 34.998254,
      "inclusive_time_rank_max": 88.048184,
      "inclusive_time_rank_min": 1.504786
    },
    {
      "path": "main/finitialize",
      "Exclusive time %": 0.001654,
      "Inclusive time %": 0.003335,
      "exclusive_time_rank_avg": 0.02006,
      "exclusive_time_rank_max": 0.020795,
      "exclusive_time_rank_min": 0.019607,
      "inclusive_time_rank_avg": 0.040444,
      "inclusive_time_rank_max": 0.040604,
      "inclusive_time_rank_min": 0.040339
    },
    {
      "path": "main/finitialize/spike-exchange",
      "Exclusive time %": 1e-06,
      "Inclusive time %": 0.0001,
      "exclusive_time_rank_avg": 7e-06,
      "exclusive_time_rank_max": 1.6e-05,
      "exclusive_time_rank_min": 5e-06,
      "inclusive_time_rank_avg": 0.00121,
      "inclusive_time_rank_max": 0.002231,
      "inclusive_time_rank_min": 0.000345
    },
    {
      "path": "main/finitialize/spike-exchange/spike-exchange",
      "Exclusive time %": 0,
      "Inclusive time %": 9.9e-05,
      "exclusive_time_rank_avg": 6e-06,
      "exclusive_time_rank_max": 1.4e-05,
      "exclusive_time_rank_min": 4e-06,
      "inclusive_time_rank_avg": 0.001203,
      "inclusive_time_rank_max": 0.002218,
      "inclusive_time_rank_min": 0.000338
    },
    {
      "path": "main/finitialize/spike-exchange/spike-exchange/imbalance",
      "Exclusive time %": 1e-06,
      "Inclusive time %": 7.2e-05,
      "exclusive_time_rank_avg": 8e-06,
      "exclusive_time_rank_max": 1.7e-05,
      "exclusive_time_rank_min": 5e-06,
      "inclusive_time_rank_avg": 0.000869,
      "inclusive_time_rank_max": 0.001872,
      "inclusive_time_rank_min": 2.8e-05
    },
    {
      "path": "main/MPI_Barrier",
      "Exclusive time %": 1.3e-05,
      "Inclusive time %": 1.3e-05,
      "exclusive_time_rank_avg": 0.000157,
      "exclusive_time_rank_max": 0.000275,
      "exclusive_time_rank_min": 8.9e-05,
      "inclusive_time_rank_avg": 0.000157,
      "inclusive_time_rank_max": 0.000275,
      "inclusive_time_rank_min": 8.9e-05
    },
    {
      "path": "main/simulation/spike-exchange/spike-exchange/imbalance/MPI_Barrier",
      "Exclusive time %": 2.88598,
      "Inclusive time %": 2.88598,
      "exclusive_time_rank_avg": 34.993794,
      "exclusive_time_rank_max": 88.040282,
      "exclusive_time_rank_min": 1.502217,
      "inclusive_time_rank_avg": 34.993794,
      "inclusive_time_rank_max": 88.040282,
      "inclusive_time_rank_min": 1.502217
    },
    {
      "path": "main/simulation/MPI_Barrier",
      "Exclusive time %": 1e-06,
      "Inclusive time %": 1e-06,
      "exclusive_time_rank_avg": 9e-06,
      "exclusive_time_rank_max": 1.2e-05,
      "exclusive_time_rank_min": 6e-06,
      "inclusive_time_rank_avg": 9e-06,
      "inclusive_time_rank_max": 1.2e-05,
      "inclusive_time_rank_min": 6e-06
    },
    {
      "path": "main/output-spike/MPI_Barrier",
      "Exclusive time %": 1e-05,
      "Inclusive time %": 1e-05,
      "exclusive_time_rank_avg": 0.000124,
      "exclusive_time_rank_max": 0.000258,
      "exclusive_time_rank_min": 6e-06,
      "inclusive_time_rank_avg": 0.000124,
      "inclusive_time_rank_max": 0.000258,
      "inclusive_time_rank_min": 6e-06
    },
    {
      "path": "main/finitialize/spike-exchange/spike-exchange/imbalance/MPI_Barrier",
      "Exclusive time %": 7.1e-05,
      "Inclusive time %": 7.1e-05,
      "exclusive_time_rank_avg": 0.00086,
      "exclusive_time_rank_max": 0.001858,
      "exclusive_time_rank_min": 1.9e-05,
      "inclusive_time_rank_avg": 0.00086,
      "inclusive_time_rank_max": 0.001858,
      "inclusive_time_rank_min": 1.9e-05
    },
    {
      "path": "main/simulation/timestep/setup-tree-matrix/cur-ch_KCaS",
      "Exclusive time %": 0.02051,
      "Inclusive time %": 0.02051,
      "exclusive_time_rank_avg": 0.24869,
      "exclusive_time_rank_max": 0.277485,
      "exclusive_time_rank_min": 0.21481,
      "inclusive_time_rank_avg": 0.24869,
      "inclusive_time_rank_max": 0.277485,
      "inclusive_time_rank_min": 0.21481
    },
    {
      "path": "main/simulation/timestep/deliver-events/net-receive-MyExp2SynNMDABB",
      "Exclusive time %": 0.047595,
      "Inclusive time %": 0.047595,
      "exclusive_time_rank_avg": 0.577104,
      "exclusive_time_rank_max": 0.619748,
      "exclusive_time_rank_min": 0.556019,
      "inclusive_time_rank_avg": 0.577104,
      "inclusive_time_rank_max": 0.619748,
      "inclusive_time_rank_min": 0.556019
    },
    {
      "path": "main/simulation/timestep/state-update/state-kBK",
      "Exclusive time %": 2.046086,
      "Inclusive time %": 2.046086,
      "exclusive_time_rank_avg": 24.809697,
      "exclusive_time_rank_max": 26.573382,
      "exclusive_time_rank_min": 23.574751,
      "inclusive_time_rank_avg": 24.809697,
      "inclusive_time_rank_max": 26.573382,
      "inclusive_time_rank_min": 23.574751
    },
    {
      "path": "main/simulation/timestep/setup-tree-matrix/cur-kdmc",
      "Exclusive time %": 0.074607,
      "Inclusive time %": 0.074607,
      "exclusive_time_rank_avg": 0.904648,
      "exclusive_time_rank_max": 0.957513,
      "exclusive_time_rank_min": 0.84481,
      "inclusive_time_rank_avg": 0.904648,
      "inclusive_time_rank_max": 0.957513,
      "inclusive_time_rank_min": 0.84481
    },
    {
      "path": "main/finitialize/cur-ch_Kdrfastngf",
      "Exclusive time %": 0,
      "Inclusive time %": 0,
      "exclusive_time_rank_avg": 5e-06,
      "exclusive_time_rank_max": 1.3e-05,
      "exclusive_time_rank_min": 3e-06,
      "inclusive_time_rank_avg": 5e-06,
      "inclusive_time_rank_max": 1.3e-05,
      "inclusive_time_rank_min": 3e-06
    },
    {
      "path": "main/finitialize/cur-kdr",
      "Exclusive time %": 2.9e-05,
      "Inclusive time %": 2.9e-05,
      "exclusive_time_rank_avg": 0.000347,
      "exclusive_time_rank_max": 0.000468,
      "exclusive_time_rank_min": 0.000283,
      "inclusive_time_rank_avg": 0.000347,
      "inclusive_time_rank_max": 0.000468,
      "inclusive_time_rank_min": 0.000283
    },
    {
      "path": "main/simulation/timestep/setup-tree-matrix/cur-ch_Kdrfastngf",
      "Exclusive time %": 0.021416,
      "Inclusive time %": 0.021416,
      "exclusive_time_rank_avg": 0.259673,
      "exclusive_time_rank_max": 0.325688,
      "exclusive_time_rank_min": 0.226386,
      "inclusive_time_rank_avg": 0.259673,
      "inclusive_time_rank_max": 0.325688,
      "inclusive_time_rank_min": 0.226386
    },
    {
      "path": "main/simulation/timestep/state-update/state-cadyn",
      "Exclusive time %": 0.020716,
      "Inclusive time %": 0.020716,
      "exclusive_time_rank_avg": 0.251188,
      "exclusive_time_rank_max": 0.291626,
      "exclusive_time_rank_min": 0.21228,
      "inclusive_time_rank_avg": 0.251188,
      "inclusive_time_rank_max": 0.291626,
      "inclusive_time_rank_min": 0.21228
    },
    {
      "path": "main/simulation/timestep",
      "Exclusive time %": 0.152296,
      "Inclusive time %": 96.983345,
      "exclusive_time_rank_avg": 1.846653,
      "exclusive_time_rank_max": 1.989782,
      "exclusive_time_rank_min": 1.737037,
      "inclusive_time_rank_avg": 1175.966183,
      "inclusive_time_rank_max": 1209.431798,
      "inclusive_time_rank_min": 1122.93139
    },
    {
      "path": "main/simulation/timestep/state-update/state-kctin",
      "Exclusive time %": 0.021687,
      "Inclusive time %": 0.021687,
      "exclusive_time_rank_avg": 0.262961,
      "exclusive_time_rank_max": 0.313346,
      "exclusive_time_rank_min": 0.230859,
      "inclusive_time_rank_avg": 0.262961,
      "inclusive_time_rank_max": 0.313346,
      "inclusive_time_rank_min": 0.230859
    },
    {
      "path": "main/simulation/timestep/deliver-events",
      "Exclusive time %": 0.384617,
      "Inclusive time %": 0.750444,
      "exclusive_time_rank_avg": 4.663651,
      "exclusive_time_rank_max": 5.005008,
      "exclusive_time_rank_min": 4.467237,
      "inclusive_time_rank_avg": 9.09947,
      "inclusive_time_rank_max": 9.604329,
      "inclusive_time_rank_min": 8.813933
    },
    {
      "path": "main/simulation/timestep/deliver-events/net-receive-MyExp2SynBB",
      "Exclusive time %": 0.057449,
      "Inclusive time %": 0.057449,
      "exclusive_time_rank_avg": 0.696598,
      "exclusive_time_rank_max": 0.725403,
      "exclusive_time_rank_min": 0.665364,
      "inclusive_time_rank_avg": 0.696598,
      "inclusive_time_rank_max": 0.725403,
      "inclusive_time_rank_min": 0.665364
    },
    {
      "path": "main/finitialize/update-net-receive-buf",
      "Exclusive time %": 3e-06,
      "Inclusive time %": 3e-06,
      "exclusive_time_rank_avg": 4e-05,
      "exclusive_time_rank_max": 6.4e-05,
      "exclusive_time_rank_min": 2.5e-05,
      "inclusive_time_rank_avg": 4e-05,
      "inclusive_time_rank_max": 6.4e-05,
      "inclusive_time_rank_min": 2.5e-05
    },
    {
      "path": "main/finitialize/cur-ch_KvAngf",
      "Exclusive time %": 0,
      "Inclusive time %": 0,
      "exclusive_time_rank_avg": 4e-06,
      "exclusive_time_rank_max": 1.4e-05,
      "exclusive_time_rank_min": 2e-06,
      "inclusive_time_rank_avg": 4e-06,
      "inclusive_time_rank_max": 1.4e-05,
      "inclusive_time_rank_min": 2e-06
    },
    {
      "path": "main/simulation/timestep/setup-tree-matrix/cur-kdr",
      "Exclusive time %": 1.315722,
      "Inclusive time %": 1.315722,
      "exclusive_time_rank_avg": 15.953709,
      "exclusive_time_rank_max": 16.91645,
      "exclusive_time_rank_min": 14.954463,
      "inclusive_time_rank_avg": 15.953709,
      "inclusive_time_rank_max": 16.91645,
      "inclusive_time_rank_min": 14.954463
    },
    {
      "path": "main/finitialize/spike-exchange/spike-exchange/communication",
      "Exclusive time %": 1.6e-05,
      "Inclusive time %": 2.7e-05,
      "exclusive_time_rank_avg": 0.000188,
      "exclusive_time_rank_max": 0.000274,
      "exclusive_time_rank_min": 7.4e-05,
      "inclusive_time_rank_avg": 0.000329,
      "inclusive_time_rank_max": 0.000351,
      "inclusive_time_rank_min": 0.000304
    },
    {
      "path": "main/simulation/timestep/setup-tree-matrix/cur-ch_KvAngf",
      "Exclusive time %": 0.016032,
      "Inclusive time %": 0.016032,
      "exclusive_time_rank_avg": 0.194393,
      "exclusive_time_rank_max": 0.231536,
      "exclusive_time_rank_min": 0.163728,
      "inclusive_time_rank_avg": 0.194393,
      "inclusive_time_rank_max": 0.231536,
      "inclusive_time_rank_min": 0.163728
    },
    {
      "path": "main/finitialize/cur-kdrcr",
      "Exclusive time %": 1e-06,
      "Inclusive time %": 1e-06,
      "exclusive_time_rank_avg": 9e-06,
      "exclusive_time_rank_max": 2.2e-05,
      "exclusive_time_rank_min": 5e-06,
      "inclusive_time_rank_avg": 9e-06,
      "inclusive_time_rank_max": 2.2e-05,
      "inclusive_time_rank_min": 5e-06
    },
    {
      "path": "main/simulation/timestep/state-update/state-kdmc",
      "Exclusive time %": 0.066479,
      "Inclusive time %": 0.066479,
      "exclusive_time_rank_avg": 0.806082,
      "exclusive_time_rank_max": 0.868089,
      "exclusive_time_rank_min": 0.758685,
      "inclusive_time_rank_avg": 0.806082,
      "inclusive_time_rank_max": 0.868089,
      "inclusive_time_rank_min": 0.758685
    },
    {
      "path": "main/simulation/timestep/state-update/state-cadad",
      "Exclusive time %": 0.956874,
      "Inclusive time %": 0.956874,
      "exclusive_time_rank_avg": 11.602518,
      "exclusive_time_rank_max": 12.089643,
      "exclusive_time_rank_min": 10.767856,
      "inclusive_time_rank_avg": 11.602518,
      "inclusive_time_rank_max": 12.089643,
      "inclusive_time_rank_min": 10.767856
    },
    {
      "path": "main/checkpoint",
      "Exclusive time %": 1e-06,
      "Inclusive time %": 1e-06,
      "exclusive_time_rank_avg": 1.1e-05,
      "exclusive_time_rank_max": 2.6e-05,
      "exclusive_time_rank_min": 9e-06,
      "inclusive_time_rank_avg": 1.1e-05,
      "inclusive_time_rank_max": 2.6e-05,
      "inclusive_time_rank_min": 9e-06
    },
    {
      "path": "main/finitialize/cur-ch_KvCaB",
      "Exclusive time %": 0,
      "Inclusive time %": 0,
      "exclusive_time_rank_avg": 5e-06,
      "exclusive_time_rank_max": 7e-06,
      "exclusive_time_rank_min": 2e-06,
      "inclusive_time_rank_avg": 5e-06,
      "inclusive_time_rank_max": 7e-06,
      "inclusive_time_rank_min": 2e-06
    },
    {
      "path": "main/simulation/timestep/deliver-events/update-net-receive-buf/net-receive-buf-order",
      "Exclusive time %": 0.035177,
      "Inclusive time %": 0.035177,
      "exclusive_time_rank_avg": 0.426541,
      "exclusive_time_rank_max": 0.480435,
      "exclusive_time_rank_min": 0.38833,
      "inclusive_time_rank_avg": 0.426541,
      "inclusive_time_rank_max": 0.480435,
      "inclusive_time_rank_min": 0.38833
    },
    {
      "path": "main/simulation/timestep/deliver-events/update-net-receive-buf",
      "Exclusive time %": 0.105232,
      "Inclusive time %": 0.14041,
      "exclusive_time_rank_avg": 1.275988,
      "exclusive_time_rank_max": 1.322996,
      "exclusive_time_rank_min": 1.184973,
      "inclusive_time_rank_avg": 1.702529,
      "inclusive_time_rank_max": 1.801461,
      "inclusive_time_rank_min": 1.595879
    },
    {
      "path": "main/simulation/timestep/setup-tree-matrix/cur-ch_KvCaB",
      "Exclusive time %": 0.021543,
      "Inclusive time %": 0.021543,
      "exclusive_time_rank_avg": 0.261216,
      "exclusive_time_rank_max": 0.324342,
      "exclusive_time_rank_min": 0.20822,
      "inclusive_time_rank_avg": 0.261216,
      "inclusive_time_rank_max": 0.324342,
      "inclusive_time_rank_min": 0.20822
    },
    {
      "path": "main/simulation/spike-exchange/spike-exchange/communication",
      "Exclusive time %": 0.001082,
      "Inclusive time %": 0.006678,
      "exclusive_time_rank_avg": 0.013125,
      "exclusive_time_rank_max": 0.014398,
      "exclusive_time_rank_min": 0.011895,
      "inclusive_time_rank_avg": 0.080973,
      "inclusive_time_rank_max": 0.088592,
      "inclusive_time_rank_min": 0.073734
    },
    {
      "path": "main/simulation/timestep/state-update/state-kdr",
      "Exclusive time %": 0.970839,
      "Inclusive time %": 0.970839,
      "exclusive_time_rank_avg": 11.771852,
      "exclusive_time_rank_max": 12.271715,
      "exclusive_time_rank_min": 11.256719,
      "inclusive_time_rank_avg": 11.771852,
      "inclusive_time_rank_max": 12.271715,
      "inclusive_time_rank_min": 11.256719
    },
    {
      "path": "main/simulation/timestep/setup-tree-matrix/cur-kdrcr",
      "Exclusive time %": 0.027638,
      "Inclusive time %": 0.027638,
      "exclusive_time_rank_avg": 0.335119,
      "exclusive_time_rank_max": 0.394731,
      "exclusive_time_rank_min": 0.284481,
      "inclusive_time_rank_avg": 0.335119,
      "inclusive_time_rank_max": 0.394731,
      "inclusive_time_rank_min": 0.284481
    },
    {
      "path": "main/simulation/timestep/state-update",
      "Exclusive time %": 0.813566,
      "Inclusive time %": 29.786757,
      "exclusive_time_rank_avg": 9.864848,
      "exclusive_time_rank_max": 10.693861,
      "exclusive_time_rank_min": 9.411642,
      "inclusive_time_rank_avg": 361.177674,
      "inclusive_time_rank_max": 368.703409,
      "inclusive_time_rank_min": 348.670609
    },
    {
      "path": "main/finitialize/cur-kdrin",
      "Exclusive time %": 1e-06,
      "Inclusive time %": 1e-06,
      "exclusive_time_rank_avg": 9e-06,
      "exclusive_time_rank_max": 1.7e-05,
      "exclusive_time_rank_min": 5e-06,
      "inclusive_time_rank_avg": 9e-06,
      "inclusive_time_rank_max": 1.7e-05,
      "inclusive_time_rank_min": 5e-06
    },
    {
      "path": "main/simulation/timestep/state-update/state-ch_KvAngf",
      "Exclusive time %": 0.017094,
      "Inclusive time %": 0.017094,
      "exclusive_time_rank_avg": 0.207276,
      "exclusive_time_rank_max": 0.244017,
      "exclusive_time_rank_min": 0.165371,
      "inclusive_time_rank_avg": 0.207276,
      "inclusive_time_rank_max": 0.244017,
      "inclusive_time_rank_min": 0.165371
    },
    {
      "path": "main/finitialize/cur-ch_Navngf",
      "Exclusive time %": 0,
      "Inclusive time %": 0,
      "exclusive_time_rank_avg": 5e-06,
      "exclusive_time_rank_max": 1.6e-05,
      "exclusive_time_rank_min": 3e-06,
      "inclusive_time_rank_avg": 5e-06,
      "inclusive_time_rank_max": 1.6e-05,
      "inclusive_time_rank_min": 3e-06
    },
    {
      "path": "main/simulation/timestep/state-update/state-cal",
      "Exclusive time %": 1.110653,
      "Inclusive time %": 1.110653,
      "exclusive_time_rank_avg": 13.46716,
      "exclusive_time_rank_max": 13.974013,
      "exclusive_time_rank_min": 12.931338,
      "inclusive_time_rank_avg": 13.46716,
      "inclusive_time_rank_max": 13.974013,
      "inclusive_time_rank_min": 12.931338
    },
    {
      "path": "main/simulation/timestep/setup-tree-matrix",
      "Exclusive time %": 2.455696,
      "Inclusive time %": 65.318433,
      "exclusive_time_rank_avg": 29.776401,
      "exclusive_time_rank_max": 32.718925,
      "exclusive_time_rank_min": 27.7518,
      "inclusive_time_rank_avg": 792.015044,
      "inclusive_time_rank_max": 818.033799,
      "inclusive_time_rank_min": 752.197616
    },
    {
      "path": "main/simulation/timestep/setup-tree-matrix/cur-ch_Navngf",
      "Exclusive time %": 0.0227,
      "Inclusive time %": 0.0227,
      "exclusive_time_rank_avg": 0.275245,
      "exclusive_time_rank_max": 0.309413,
      "exclusive_time_rank_min": 0.235124,
      "inclusive_time_rank_avg": 0.275245,
      "inclusive_time_rank_max": 0.309413,
      "inclusive_time_rank_min": 0.235124
    },
    {
      "path": "main/finitialize/spike-exchange/spike-exchange/communication/MPI_Allgather",
      "Exclusive time %": 1.2e-05,
      "Inclusive time %": 1.2e-05,
      "exclusive_time_rank_avg": 0.000141,
      "exclusive_time_rank_max": 0.000269,
      "exclusive_time_rank_min": 4.6e-05,
      "inclusive_time_rank_avg": 0.000141,
      "inclusive_time_rank_max": 0.000269,
      "inclusive_time_rank_min": 4.6e-05
    },
    {
      "path": "main/simulation/timestep/state-update/state-kdrcr",
      "Exclusive time %": 0.023369,
      "Inclusive time %": 0.023369,
      "exclusive_time_rank_avg": 0.283354,
      "exclusive_time_rank_max": 0.331379,
      "exclusive_time_rank_min": 0.246953,
      "inclusive_time_rank_avg": 0.283354,
      "inclusive_time_rank_max": 0.331379,
      "inclusive_time_rank_min": 0.246953
    },
    {
      "path": "main/simulation/timestep/setup-tree-matrix/cur-kdrin",
      "Exclusive time %": 0.032393,
      "Inclusive time %": 0.032393,
      "exclusive_time_rank_avg": 0.392774,
      "exclusive_time_rank_max": 0.423247,
      "exclusive_time_rank_min": 0.330936,
      "inclusive_time_rank_avg": 0.392774,
      "inclusive_time_rank_max": 0.423247,
      "inclusive_time_rank_min": 0.330936
    },
    {
      "path": "main/finitialize/cur-pas",
      "Exclusive time %": 1e-05,
      "Inclusive time %": 1e-05,
      "exclusive_time_rank_avg": 0.000118,
      "exclusive_time_rank_max": 0.00017,
      "exclusive_time_rank_min": 8.6e-05,
      "inclusive_time_rank_avg": 0.000118,
      "inclusive_time_rank_max": 0.00017,
      "inclusive_time_rank_min": 8.6e-05
    },
    {
      "path": "main/finitialize/cur-hin",
      "Exclusive time %": 1e-06,
      "Inclusive time %": 1e-06,
      "exclusive_time_rank_avg": 1e-05,
      "exclusive_time_rank_max": 3.5e-05,
      "exclusive_time_rank_min": 6e-06,
      "inclusive_time_rank_avg": 1e-05,
      "inclusive_time_rank_max": 3.5e-05,
      "inclusive_time_rank_min": 6e-06
    },
    {
      "path": "main/simulation/spike-exchange/spike-exchange/communication/MPI_Allgather",
      "Exclusive time %": 0.001563,
      "Inclusive time %": 0.001563,
      "exclusive_time_rank_avg": 0.018954,
      "exclusive_time_rank_max": 0.025196,
      "exclusive_time_rank_min": 0.01165,
      "inclusive_time_rank_avg": 0.018954,
      "inclusive_time_rank_max": 0.025196,
      "inclusive_time_rank_min": 0.01165
    },
    {
      "path": "main/simulation/timestep/setup-tree-matrix/cur-hin",
      "Exclusive time %": 0.017063,
      "Inclusive time %": 0.017063,
      "exclusive_time_rank_avg": 0.206896,
      "exclusive_time_rank_max": 0.228232,
      "exclusive_time_rank_min": 0.181902,
      "inclusive_time_rank_avg": 0.206896,
      "inclusive_time_rank_max": 0.228232,
      "inclusive_time_rank_min": 0.181902
    },
    {
      "path": "main/simulation/timestep/setup-tree-matrix/cur-pas",
      "Exclusive time %": 0.607381,
      "Inclusive time %": 0.607381,
      "exclusive_time_rank_avg": 7.364759,
      "exclusive_time_rank_max": 8.400505,
      "exclusive_time_rank_min": 6.692717,
      "inclusive_time_rank_avg": 7.364759,
      "inclusive_time_rank_max": 8.400505,
      "inclusive_time_rank_min": 6.692717
    },
    {
      "path": "main/simulation/timestep/state-update/state-kdrin",
      "Exclusive time %": 0.02384,
      "Inclusive time %": 0.02384,
      "exclusive_time_rank_avg": 0.289067,
      "exclusive_time_rank_max": 0.323478,
      "exclusive_time_rank_min": 0.242016,
      "inclusive_time_rank_avg": 0.289067,
      "inclusive_time_rank_max": 0.323478,
      "inclusive_time_rank_min": 0.242016
    },
    {
      "path": "main/simulation/timestep/state-update/state-ch_KvCaB",
      "Exclusive time %": 0.014271,
      "Inclusive time %": 0.014271,
      "exclusive_time_rank_avg": 0.173042,
      "exclusive_time_rank_max": 0.199497,
      "exclusive_time_rank_min": 0.141301,
      "inclusive_time_rank_avg": 0.173042,
      "inclusive_time_rank_max": 0.199497,
      "inclusive_time_rank_min": 0.141301
    },
    {
      "path": "main/finitialize/cur-ih",
      "Exclusive time %": 3e-06,
      "Inclusive time %": 3e-06,
      "exclusive_time_rank_avg": 4e-05,
      "exclusive_time_rank_max": 5.2e-05,
      "exclusive_time_rank_min": 2.8e-05,
      "inclusive_time_rank_avg": 4e-05,
      "inclusive_time_rank_max": 5.2e-05,
      "inclusive_time_rank_min": 2.8e-05
    },
    {
      "path": "main/MPI_Comm_free",
      "Exclusive time %": 2.8e-05,
      "Inclusive time %": 2.8e-05,
      "exclusive_time_rank_avg": 0.000338,
      "exclusive_time_rank_max": 0.00049,
      "exclusive_time_rank_min": 1.4e-05,
      "inclusive_time_rank_avg": 0.000338,
      "inclusive_time_rank_max": 0.00049,
      "inclusive_time_rank_min": 1.4e-05
    },
    {
      "path": "main/finitialize/cur-MyExp2SynBB",
      "Exclusive time %": 0.000586,
      "Inclusive time %": 0.000586,
      "exclusive_time_rank_avg": 0.007104,
      "exclusive_time_rank_max": 0.007434,
      "exclusive_time_rank_min": 0.006887,
      "inclusive_time_rank_avg": 0.007104,
      "inclusive_time_rank_max": 0.007434,
      "inclusive_time_rank_min": 0.006887
    },
    {
      "path": "main/simulation/timestep/setup-tree-matrix/cur-ih",
      "Exclusive time %": 0.158143,
      "Inclusive time %": 0.158143,
      "exclusive_time_rank_avg": 1.917548,
      "exclusive_time_rank_max": 2.261272,
      "exclusive_time_rank_min": 1.735428,
      "inclusive_time_rank_avg": 1.917548,
      "inclusive_time_rank_max": 2.261272,
      "inclusive_time_rank_min": 1.735428
    },
    {
      "path": "main/simulation/timestep/state-update/state-MyExp2SynBB",
      "Exclusive time %": 8.108358,
      "Inclusive time %": 8.108358,
      "exclusive_time_rank_avg": 98.317444,
      "exclusive_time_rank_max": 101.881287,
      "exclusive_time_rank_min": 94.774904,
      "inclusive_time_rank_avg": 98.317444,
      "inclusive_time_rank_max": 101.881287,
      "inclusive_time_rank_min": 94.774904
    },
    {
      "path": "main/simulation/timestep/state-update/state-cancr",
      "Exclusive time %": 0.02643,
      "Inclusive time %": 0.02643,
      "exclusive_time_rank_avg": 0.320479,
      "exclusive_time_rank_max": 0.398219,
      "exclusive_time_rank_min": 0.290713,
      "inclusive_time_rank_avg": 0.320479,
      "inclusive_time_rank_max": 0.398219,
      "inclusive_time_rank_min": 0.290713
    },
    {
      "path": "main/finitialize/cur-na_ion",
      "Exclusive time %": 6e-06,
      "Inclusive time %": 6e-06,
      "exclusive_time_rank_avg": 7.6e-05,
      "exclusive_time_rank_max": 0.000118,
      "exclusive_time_rank_min": 4.8e-05,
      "inclusive_time_rank_avg": 7.6e-05,
      "inclusive_time_rank_max": 0.000118,
      "inclusive_time_rank_min": 4.8e-05
    },
    {
      "path": "main/finitialize/cur-hd",
      "Exclusive time %": 2e-05,
      "Inclusive time %": 2e-05,
      "exclusive_time_rank_avg": 0.00024,
      "exclusive_time_rank_max": 0.000277,
      "exclusive_time_rank_min": 0.000199,
      "inclusive_time_rank_avg": 0.00024,
      "inclusive_time_rank_max": 0.000277,
      "inclusive_time_rank_min": 0.000199
    },
    {
      "path": "main/simulation/timestep/setup-tree-matrix/cur-MyExp2SynBB",
      "Exclusive time %": 22.755275,
      "Inclusive time %": 22.755275,
      "exclusive_time_rank_avg": 275.917827,
      "exclusive_time_rank_max": 282.73545,
      "exclusive_time_rank_min": 262.977591,
      "inclusive_time_rank_avg": 275.917827,
      "inclusive_time_rank_max": 282.73545,
      "inclusive_time_rank_min": 262.977591
    },
    {
      "path": "main/simulation/timestep/setup-tree-matrix/cur-na_ion",
      "Exclusive time %": 0.319626,
      "Inclusive time %": 0.319626,
      "exclusive_time_rank_avg": 3.875603,
      "exclusive_time_rank_max": 4.301688,
      "exclusive_time_rank_min": 3.597454,
      "inclusive_time_rank_avg": 3.875603,
      "inclusive_time_rank_max": 4.301688,
      "inclusive_time_rank_min": 3.597454
    },
    {
      "path": "main/output-spike/MPI_Initialized",
      "Exclusive time %": 0,
      "Inclusive time %": 0,
      "exclusive_time_rank_avg": 4e-06,
      "exclusive_time_rank_max": 1.1e-05,
      "exclusive_time_rank_min": 3e-06,
      "inclusive_time_rank_avg": 4e-06,
      "inclusive_time_rank_max": 1.1e-05,
      "inclusive_time_rank_min": 3e-06
    },
    {
      "path": "main/simulation/timestep/state-update/state-ch_Navngf",
      "Exclusive time %": 0.021082,
      "Inclusive time %": 0.021082,
      "exclusive_time_rank_avg": 0.255624,
      "exclusive_time_rank_max": 0.287878,
      "exclusive_time_rank_min": 0.222986,
      "inclusive_time_rank_avg": 0.255624,
      "inclusive_time_rank_max": 0.287878,
      "inclusive_time_rank_min": 0.222986
    },
    {
      "path": "main/simulation/timestep/setup-tree-matrix/cur-hd",
      "Exclusive time %": 1.002702,
      "Inclusive time %": 1.002702,
      "exclusive_time_rank_avg": 12.158204,
      "exclusive_time_rank_max": 12.646439,
      "exclusive_time_rank_min": 11.494786,
      "inclusive_time_rank_avg": 12.158204,
      "inclusive_time_rank_max": 12.646439,
      "inclusive_time_rank_min": 11.494786
    },
    {
      "path": "main/simulation/timestep/state-update/state-MyExp2SynNMDABB",
      "Exclusive time %": 9.973992,
      "Inclusive time %": 9.973992,
      "exclusive_time_rank_avg": 120.939083,
      "exclusive_time_rank_max": 126.730764,
      "exclusive_time_rank_min": 114.939598,
      "inclusive_time_rank_avg": 120.939083,
      "inclusive_time_rank_max": 126.730764,
      "inclusive_time_rank_min": 114.939598
    },
    {
      "path": "main/MPI_Initialized",
      "Exclusive time %": 0,
      "Inclusive time %": 0,
      "exclusive_time_rank_avg": 5e-06,
      "exclusive_time_rank_max": 1.6e-05,
      "exclusive_time_rank_min": 4e-06,
      "inclusive_time_rank_avg": 5e-06,
      "inclusive_time_rank_max": 1.6e-05,
      "inclusive_time_rank_min": 4e-06
    },
    {
      "path": "main/MPI_Finalize",
      "Exclusive time %": 0.000192,
      "Inclusive time %": 0.000192,
      "exclusive_time_rank_avg": 0.002334,
      "exclusive_time_rank_max": 0.003059,
      "exclusive_time_rank_min": 0.001608,
      "inclusive_time_rank_avg": 0.002334,
      "inclusive_time_rank_max": 0.003059,
      "inclusive_time_rank_min": 0.001608
    },
    {
      "path": "main/finitialize/cur-MyExp2SynNMDABB",
      "Exclusive time %": 0.000736,
      "Inclusive time %": 0.000736,
      "exclusive_time_rank_avg": 0.00892,
      "exclusive_time_rank_max": 0.009165,
      "exclusive_time_rank_min": 0.008461,
      "inclusive_time_rank_avg": 0.00892,
      "inclusive_time_rank_max": 0.009165,
      "inclusive_time_rank_min": 0.008461
    },
    {
      "path": "main/finitialize/cur-ican",
      "Exclusive time %": 0,
      "Inclusive time %": 0,
      "exclusive_time_rank_avg": 6e-06,
      "exclusive_time_rank_max": 1.9e-05,
      "exclusive_time_rank_min": 4e-06,
      "inclusive_time_rank_avg": 6e-06,
      "inclusive_time_rank_max": 1.9e-05,
      "inclusive_time_rank_min": 4e-06
    },
    {
      "path": "main/simulation/timestep/state-update/state-canin",
      "Exclusive time %": 0.018405,
      "Inclusive time %": 0.018405,
      "exclusive_time_rank_avg": 0.223166,
      "exclusive_time_rank_max": 0.257773,
      "exclusive_time_rank_min": 0.189145,
      "inclusive_time_rank_avg": 0.223166,
      "inclusive_time_rank_max": 0.257773,
      "inclusive_time_rank_min": 0.189145
    },
    {
      "path": "main/simulation/timestep/setup-tree-matrix/cur-ican",
      "Exclusive time %": 0.021005,
      "Inclusive time %": 0.021005,
      "exclusive_time_rank_avg": 0.254698,
      "exclusive_time_rank_max": 0.291825,
      "exclusive_time_rank_min": 0.230909,
      "inclusive_time_rank_avg": 0.254698,
      "inclusive_time_rank_max": 0.291825,
      "inclusive_time_rank_min": 0.230909
    },
    {
      "path": "main/finitialize/cur-k_ion",
      "Exclusive time %": 7e-06,
      "Inclusive time %": 7e-06,
      "exclusive_time_rank_avg": 8.2e-05,
      "exclusive_time_rank_max": 0.000115,
      "exclusive_time_rank_min": 4.8e-05,
      "inclusive_time_rank_avg": 8.2e-05,
      "inclusive_time_rank_max": 0.000115,
      "inclusive_time_rank_min": 4.8e-05
    },
    {
      "path": "main/simulation/timestep/state-update/state-Nafcr",
      "Exclusive time %": 0.029162,
      "Inclusive time %": 0.029162,
      "exclusive_time_rank_avg": 0.353607,
      "exclusive_time_rank_max": 0.406235,
      "exclusive_time_rank_min": 0.308338,
      "inclusive_time_rank_avg": 0.353607,
      "inclusive_time_rank_max": 0.406235,
      "inclusive_time_rank_min": 0.308338
    },
    {
      "path": "main/simulation/timestep/setup-tree-matrix/cur-MyExp2SynNMDABB",
      "Exclusive time %": 27.353827,
      "Inclusive time %": 27.353827,
      "exclusive_time_rank_avg": 331.677319,
      "exclusive_time_rank_max": 355.808377,
      "exclusive_time_rank_min": 310.738609,
      "inclusive_time_rank_avg": 331.677319,
      "inclusive_time_rank_max": 355.808377,
      "inclusive_time_rank_min": 310.738609
    },
    {
      "path": "main/output-spike/MPI_Alltoall",
      "Exclusive time %": 8.5e-05,
      "Inclusive time %": 8.5e-05,
      "exclusive_time_rank_avg": 0.001029,
      "exclusive_time_rank_max": 0.001141,
      "exclusive_time_rank_min": 0.000943,
      "inclusive_time_rank_avg": 0.001029,
      "inclusive_time_rank_max": 0.001141,
      "inclusive_time_rank_min": 0.000943
    },
    {
      "path": "main/simulation/timestep/setup-tree-matrix/cur-k_ion",
      "Exclusive time %": 0.296956,
      "Inclusive time %": 0.296956,
      "exclusive_time_rank_avg": 3.600719,
      "exclusive_time_rank_max": 3.787329,
      "exclusive_time_rank_min": 3.395334,
      "inclusive_time_rank_avg": 3.600719,
      "inclusive_time_rank_max": 3.787329,
      "inclusive_time_rank_min": 3.395334
    },
    {
      "path": "main/finitialize/cur-iCcr",
      "Exclusive time %": 1e-06,
      "Inclusive time %": 1e-06,
      "exclusive_time_rank_avg": 1.1e-05,
      "exclusive_time_rank_max": 2.4e-05,
      "exclusive_time_rank_min": 3e-06,
      "inclusive_time_rank_avg": 1.1e-05,
      "inclusive_time_rank_max": 2.4e-05,
      "inclusive_time_rank_min": 3e-06
    },
    {
      "path": "main/finitialize/cur-Nafcr",
      "Exclusive time %": 1e-06,
      "Inclusive time %": 1e-06,
      "exclusive_time_rank_avg": 1.8e-05,
      "exclusive_time_rank_max": 8e-05,
      "exclusive_time_rank_min": 9e-06,
      "inclusive_time_rank_avg": 1.8e-05,
      "inclusive_time_rank_max": 8e-05,
      "inclusive_time_rank_min": 9e-06
    },
    {
      "path": "main/simulation/timestep/setup-tree-matrix/cur-iCcr",
      "Exclusive time %": 0.019397,
      "Inclusive time %": 0.019397,
      "exclusive_time_rank_avg": 0.235196,
      "exclusive_time_rank_max": 0.268142,
      "exclusive_time_rank_min": 0.215133,
      "inclusive_time_rank_avg": 0.235196,
      "inclusive_time_rank_max": 0.268142,
      "inclusive_time_rank_min": 0.215133
    },
    {
      "path": "main/simulation/timestep/state-update/state-Nafx",
      "Exclusive time %": 0.03292,
      "Inclusive time %": 0.03292,
      "exclusive_time_rank_avg": 0.399172,
      "exclusive_time_rank_max": 0.442319,
      "exclusive_time_rank_min": 0.33243,
      "inclusive_time_rank_avg": 0.399172,
      "inclusive_time_rank_max": 0.442319,
      "inclusive_time_rank_min": 0.33243
    },
    {
      "path": "main/simulation/timestep/state-update/state-can",
      "Exclusive time %": 1.319166,
      "Inclusive time %": 1.319166,
      "exclusive_time_rank_avg": 15.995473,
      "exclusive_time_rank_max": 16.639347,
      "exclusive_time_rank_min": 15.189036,
      "inclusive_time_rank_avg": 15.995473,
      "inclusive_time_rank_max": 16.639347,
      "inclusive_time_rank_min": 15.189036
    },
    {
      "path": "main/finitialize/cur-IKscr",
      "Exclusive time %": 1e-06,
      "Inclusive time %": 1e-06,
      "exclusive_time_rank_avg": 1e-05,
      "exclusive_time_rank_max": 3e-05,
      "exclusive_time_rank_min": 6e-06,
      "inclusive_time_rank_avg": 1e-05,
      "inclusive_time_rank_max": 3e-05,
      "inclusive_time_rank_min": 6e-06
    },
    {
      "path": "main/simulation/timestep/setup-tree-matrix/cur-Nafcr",
      "Exclusive time %": 0.033092,
      "Inclusive time %": 0.033092,
      "exclusive_time_rank_avg": 0.401258,
      "exclusive_time_rank_max": 0.468768,
      "exclusive_time_rank_min": 0.353965,
      "inclusive_time_rank_avg": 0.401258,
      "inclusive_time_rank_max": 0.468768,
      "inclusive_time_rank_min": 0.353965
    },
    {
      "path": "main/output-spike/MPI_Alltoallv",
      "Exclusive time %": 3.2e-05,
      "Inclusive time %": 3.2e-05,
      "exclusive_time_rank_avg": 0.000383,
      "exclusive_time_rank_max": 0.000509,
      "exclusive_time_rank_min": 0.000287,
      "inclusive_time_rank_avg": 0.000383,
      "inclusive_time_rank_max": 0.000509,
      "inclusive_time_rank_min": 0.000287
    },
    {
      "path": "main/simulation/timestep/setup-tree-matrix/cur-IKscr",
      "Exclusive time %": 0.016832,
      "Inclusive time %": 0.016832,
      "exclusive_time_rank_avg": 0.204094,
      "exclusive_time_rank_max": 0.224632,
      "exclusive_time_rank_min": 0.180724,
      "inclusive_time_rank_avg": 0.204094,
      "inclusive_time_rank_max": 0.224632,
      "inclusive_time_rank_min": 0.180724
    },
    {
      "path": "main/simulation/timestep/state-update/state-hin",
      "Exclusive time %": 0.015954,
      "Inclusive time %": 0.015954,
      "exclusive_time_rank_avg": 0.193447,
      "exclusive_time_rank_max": 0.219841,
      "exclusive_time_rank_min": 0.164807,
      "inclusive_time_rank_avg": 0.193447,
      "inclusive_time_rank_max": 0.219841,
      "inclusive_time_rank_min": 0.164807
    },
    {
      "path": "main/simulation/timestep/state-update/state-nap",
      "Exclusive time %": 0.014252,
      "Inclusive time %": 0.014252,
      "exclusive_time_rank_avg": 0.172816,
      "exclusive_time_rank_max": 0.217915,
      "exclusive_time_rank_min": 0.144134,
      "inclusive_time_rank_avg": 0.172816,
      "inclusive_time_rank_max": 0.217915,
      "inclusive_time_rank_min": 0.144134
    },
    {
      "path": "main/finitialize/cur-Nafx",
      "Exclusive time %": 1e-06,
      "Inclusive time %": 1e-06,
      "exclusive_time_rank_avg": 9e-06,
      "exclusive_time_rank_max": 1.3e-05,
      "exclusive_time_rank_min": 5e-06,
      "inclusive_time_rank_avg": 9e-06,
      "inclusive_time_rank_max": 1.3e-05,
      "inclusive_time_rank_min": 5e-06
    },
    {
      "path": "main/MPI_Comm_dup",
      "Exclusive time %": 9e-06,
      "Inclusive time %": 9e-06,
      "exclusive_time_rank_avg": 0.000115,
      "exclusive_time_rank_max": 0.000237,
      "exclusive_time_rank_min": 2.1e-05,
      "inclusive_time_rank_avg": 0.000115,
      "inclusive_time_rank_max": 0.000237,
      "inclusive_time_rank_min": 2.1e-05
    },
    {
      "path": "main/finitialize/cur-IKsin",
      "Exclusive time %": 1e-06,
      "Inclusive time %": 1e-06,
      "exclusive_time_rank_avg": 8e-06,
      "exclusive_time_rank_max": 3e-05,
      "exclusive_time_rank_min": 4e-06,
      "inclusive_time_rank_avg": 8e-06,
      "inclusive_time_rank_max": 3e-05,
      "inclusive_time_rank_min": 4e-06
    },
    {
      "path": "main/simulation/timestep/state-update/state-catcb",
      "Exclusive time %": 0.022658,
      "Inclusive time %": 0.022658,
      "exclusive_time_rank_avg": 0.274743,
      "exclusive_time_rank_max": 0.305573,
      "exclusive_time_rank_min": 0.252306,
      "inclusive_time_rank_avg": 0.274743,
      "inclusive_time_rank_max": 0.305573,
      "inclusive_time_rank_min": 0.252306
    },
    {
      "path": "main/finitialize/cur-ca_ion",
      "Exclusive time %": 6e-06,
      "Inclusive time %": 6e-06,
      "exclusive_time_rank_avg": 6.9e-05,
      "exclusive_time_rank_max": 0.000103,
      "exclusive_time_rank_min": 4e-05,
      "inclusive_time_rank_avg": 6.9e-05,
      "inclusive_time_rank_max": 0.000103,
      "inclusive_time_rank_min": 4e-05
    },
    {
      "path": "main/simulation/timestep/setup-tree-matrix/cur-IKsin",
      "Exclusive time %": 0.019043,
      "Inclusive time %": 0.019043,
      "exclusive_time_rank_avg": 0.230909,
      "exclusive_time_rank_max": 0.266384,
      "exclusive_time_rank_min": 0.197563,
      "inclusive_time_rank_avg": 0.230909,
      "inclusive_time_rank_max": 0.266384,
      "inclusive_time_rank_min": 0.197563
    },
    {
      "path": "main/simulation/timestep/setup-tree-matrix/cur-Nafx",
      "Exclusive time %": 0.035176,
      "Inclusive time %": 0.035176,
      "exclusive_time_rank_avg": 0.426523,
      "exclusive_time_rank_max": 0.49146,
      "exclusive_time_rank_min": 0.367774,
      "inclusive_time_rank_avg": 0.426523,
      "inclusive_time_rank_max": 0.49146,
      "inclusive_time_rank_min": 0.367774
    },
    {
      "path": "main/simulation/timestep/state-update/state-nax",
      "Exclusive time %": 1.426505,
      "Inclusive time %": 1.426505,
      "exclusive_time_rank_avg": 17.297007,
      "exclusive_time_rank_max": 17.992102,
      "exclusive_time_rank_min": 16.467236,
      "inclusive_time_rank_avg": 17.297007,
      "inclusive_time_rank_max": 17.992102,
      "inclusive_time_rank_min": 16.467236
    },
    {
      "path": "main/finitialize/cur-nap",
      "Exclusive time %": 0,
      "Inclusive time %": 0,
      "exclusive_time_rank_avg": 4e-06,
      "exclusive_time_rank_max": 6e-06,
      "exclusive_time_rank_min": 2e-06,
      "inclusive_time_rank_avg": 4e-06,
      "inclusive_time_rank_max": 6e-06,
      "inclusive_time_rank_min": 2e-06
    },
    {
      "path": "main/finitialize/cur-kap",
      "Exclusive time %": 3.1e-05,
      "Inclusive time %": 3.1e-05,
      "exclusive_time_rank_avg": 0.000371,
      "exclusive_time_rank_max": 0.000465,
      "exclusive_time_rank_min": 0.000335,
      "inclusive_time_rank_avg": 0.000371,
      "inclusive_time_rank_max": 0.000465,
      "inclusive_time_rank_min": 0.000335
    },
    {
      "path": "main/simulation/timestep/state-update/state-cat",
      "Exclusive time %": 0.083832,
      "Inclusive time %": 0.083832,
      "exclusive_time_rank_avg": 1.016505,
      "exclusive_time_rank_max": 1.178971,
      "exclusive_time_rank_min": 0.918403,
      "inclusive_time_rank_avg": 1.016505,
      "inclusive_time_rank_max": 1.178971,
      "inclusive_time_rank_min": 0.918403
    },
    {
      "path": "main/simulation/timestep/setup-tree-matrix/cur-kap",
      "Exclusive time %": 1.517199,
      "Inclusive time %": 1.517199,
      "exclusive_time_rank_avg": 18.396712,
      "exclusive_time_rank_max": 19.149314,
      "exclusive_time_rank_min": 17.490299,
      "inclusive_time_rank_avg": 18.396712,
      "inclusive_time_rank_max": 19.149314,
      "inclusive_time_rank_min": 17.490299
    },
    {
      "path": "main/output-spike/MPI_Exscan",
      "Exclusive time %": 3e-05,
      "Inclusive time %": 3e-05,
      "exclusive_time_rank_avg": 0.00036,
      "exclusive_time_rank_max": 0.000544,
      "exclusive_time_rank_min": 1.3e-05,
      "inclusive_time_rank_avg": 0.00036,
      "inclusive_time_rank_max": 0.000544,
      "inclusive_time_rank_min": 1.3e-05
    },
    {
      "path": "main/simulation/timestep/state-update/state-savedist",
      "Exclusive time %": 0.014297,
      "Inclusive time %": 0.014297,
      "exclusive_time_rank_avg": 0.173354,
      "exclusive_time_rank_max": 0.194112,
      "exclusive_time_rank_min": 0.144338,
      "inclusive_time_rank_avg": 0.173354,
      "inclusive_time_rank_max": 0.194112,
      "inclusive_time_rank_min": 0.144338
    },
    {
      "path": "main/simulation/timestep/setup-tree-matrix/cur-nap",
      "Exclusive time %": 0.017257,
      "Inclusive time %": 0.017257,
      "exclusive_time_rank_avg": 0.209247,
      "exclusive_time_rank_max": 0.246346,
      "exclusive_time_rank_min": 0.185497,
      "inclusive_time_rank_avg": 0.209247,
      "inclusive_time_rank_max": 0.246346,
      "inclusive_time_rank_min": 0.185497
    },
    {
      "path": "main/finitialize/cur-kapcb",
      "Exclusive time %": 1e-06,
      "Inclusive time %": 1e-06,
      "exclusive_time_rank_avg": 7e-06,
      "exclusive_time_rank_max": 1.9e-05,
      "exclusive_time_rank_min": 5e-06,
      "inclusive_time_rank_avg": 7e-06,
      "inclusive_time_rank_max": 1.9e-05,
      "inclusive_time_rank_min": 5e-06
    },
    {
      "path": "main/finitialize/cur-nax",
      "Exclusive time %": 2.6e-05,
      "Inclusive time %": 2.6e-05,
      "exclusive_time_rank_avg": 0.000314,
      "exclusive_time_rank_max": 0.000437,
      "exclusive_time_rank_min": 0.00016,
      "inclusive_time_rank_avg": 0.000314,
      "inclusive_time_rank_max": 0.000437,
      "inclusive_time_rank_min": 0.00016
    },
    {
      "path": "main/simulation/timestep/setup-tree-matrix/cur-kapcb",
      "Exclusive time %": 0.027317,
      "Inclusive time %": 0.027317,
      "exclusive_time_rank_avg": 0.331234,
      "exclusive_time_rank_max": 0.372442,
      "exclusive_time_rank_min": 0.300319,
      "inclusive_time_rank_avg": 0.331234,
      "inclusive_time_rank_max": 0.372442,
      "inclusive_time_rank_min": 0.300319
    },
    {
      "path": "main/simulation/timestep/state-update/state-ch_CavL",
      "Exclusive time %": 0.014766,
      "Inclusive time %": 0.014766,
      "exclusive_time_rank_avg": 0.179039,
      "exclusive_time_rank_max": 0.215828,
      "exclusive_time_rank_min": 0.154363,
      "inclusive_time_rank_avg": 0.179039,
      "inclusive_time_rank_max": 0.215828,
      "inclusive_time_rank_min": 0.154363
    },
    {
      "path": "main/simulation/timestep/matrix-solver",
      "Exclusive time %": 0.634434,
      "Inclusive time %": 0.634434,
      "exclusive_time_rank_avg": 7.692797,
      "exclusive_time_rank_max": 9.004212,
      "exclusive_time_rank_min": 6.976214,
      "inclusive_time_rank_avg": 7.692797,
      "inclusive_time_rank_max": 9.004212,
      "inclusive_time_rank_min": 6.976214
    },
    {
      "path": "main/simulation/timestep/setup-tree-matrix/cur-ca_ion",
      "Exclusive time %": 0.290024,
      "Inclusive time %": 0.290024,
      "exclusive_time_rank_avg": 3.516673,
      "exclusive_time_rank_max": 3.68426,
      "exclusive_time_rank_min": 3.330641,
      "inclusive_time_rank_avg": 3.516673,
      "inclusive_time_rank_max": 3.68426,
      "inclusive_time_rank_min": 3.330641
    },
    {
      "path": "main/output-spike/MPI_File_open",
      "Exclusive time %": 0.001147,
      "Inclusive time %": 0.001147,
      "exclusive_time_rank_avg": 0.013906,
      "exclusive_time_rank_max": 0.01401,
      "exclusive_time_rank_min": 0.013822,
      "inclusive_time_rank_avg": 0.013906,
      "inclusive_time_rank_max": 0.01401,
      "inclusive_time_rank_min": 0.013822
    },
    {
      "path": "main/simulation/timestep/state-update/state-ih",
      "Exclusive time %": 0.204822,
      "Inclusive time %": 0.204822,
      "exclusive_time_rank_avg": 2.483562,
      "exclusive_time_rank_max": 2.605733,
      "exclusive_time_rank_min": 2.338092,
      "inclusive_time_rank_avg": 2.483562,
      "inclusive_time_rank_max": 2.605733,
      "inclusive_time_rank_min": 2.338092
    },
    {
      "path": "main/finitialize/cur-kapin",
      "Exclusive time %": 0,
      "Inclusive time %": 0,
      "exclusive_time_rank_avg": 5e-06,
      "exclusive_time_rank_max": 1e-05,
      "exclusive_time_rank_min": 3e-06,
      "inclusive_time_rank_avg": 5e-06,
      "inclusive_time_rank_max": 1e-05,
      "inclusive_time_rank_min": 3e-06
    },
    {
      "path": "main/simulation/timestep/setup-tree-matrix/cur-nax",
      "Exclusive time %": 1.637558,
      "Inclusive time %": 1.637558,
      "exclusive_time_rank_avg": 19.85612,
      "exclusive_time_rank_max": 20.846078,
      "exclusive_time_rank_min": 18.429312,
      "inclusive_time_rank_avg": 19.85612,
      "inclusive_time_rank_max": 20.846078,
      "inclusive_time_rank_min": 18.429312
    },
    {
      "path": "main/simulation/timestep/deliver-events/check-threshold",
      "Exclusive time %": 0.031578,
      "Inclusive time %": 0.031578,
      "exclusive_time_rank_avg": 0.382893,
      "exclusive_time_rank_max": 0.415767,
      "exclusive_time_rank_min": 0.351395,
      "inclusive_time_rank_avg": 0.382893,
      "inclusive_time_rank_max": 0.415767,
      "inclusive_time_rank_min": 0.351395
    },
    {
      "path": "main/simulation/timestep/setup-tree-matrix/cur-kapin",
      "Exclusive time %": 0.020047,
      "Inclusive time %": 0.020047,
      "exclusive_time_rank_avg": 0.243083,
      "exclusive_time_rank_max": 0.268878,
      "exclusive_time_rank_min": 0.218239,
      "inclusive_time_rank_avg": 0.243083,
      "inclusive_time_rank_max": 0.268878,
      "inclusive_time_rank_min": 0.218239
    },
    {
      "path": "main/simulation/timestep/state-update/state-ch_CavN",
      "Exclusive time %": 0.016855,
      "Inclusive time %": 0.016855,
      "exclusive_time_rank_avg": 0.204377,
      "exclusive_time_rank_max": 0.231846,
      "exclusive_time_rank_min": 0.177593,
      "inclusive_time_rank_avg": 0.204377,
      "inclusive_time_rank_max": 0.231846,
      "inclusive_time_rank_min": 0.177593
    },
    {
      "path": "main/simulation/timestep/second-order-cur",
      "Exclusive time %": 0.017799,
      "Inclusive time %": 0.017799,
      "exclusive_time_rank_avg": 0.21582,
      "exclusive_time_rank_max": 0.360274,
      "exclusive_time_rank_min": 0.168679,
      "inclusive_time_rank_avg": 0.21582,
      "inclusive_time_rank_max": 0.360274,
      "inclusive_time_rank_min": 0.168679
    },
    {
      "path": "main/finitialize/cur-hi_ion",
      "Exclusive time %": 0,
      "Inclusive time %": 0,
      "exclusive_time_rank_avg": 2e-06,
      "exclusive_time_rank_max": 1.5e-05,
      "exclusive_time_rank_min": 1e-06,
      "inclusive_time_rank_avg": 2e-06,
      "inclusive_time_rank_max": 1.5e-05,
      "inclusive_time_rank_min": 1e-06
    },
    {
      "path": "main/output-spike/MPI_File_write_at_all",
      "Exclusive time %": 0.002495,
      "Inclusive time %": 0.002495,
      "exclusive_time_rank_avg": 0.030256,
      "exclusive_time_rank_max": 0.058332,
      "exclusive_time_rank_min": 0.005721,
      "inclusive_time_rank_avg": 0.030256,
      "inclusive_time_rank_max": 0.058332,
      "inclusive_time_rank_min": 0.005721
    },
    {
      "path": "main/finitialize/cur-kBK",
      "Exclusive time %": 3e-05,
      "Inclusive time %": 3e-05,
      "exclusive_time_rank_avg": 0.000359,
      "exclusive_time_rank_max": 0.000533,
      "exclusive_time_rank_min": 0.000319,
      "inclusive_time_rank_avg": 0.000359,
      "inclusive_time_rank_max": 0.000533,
      "inclusive_time_rank_min": 0.000319
    },
    {
      "path": "main/simulation/timestep/setup-tree-matrix/cur-hi_ion",
      "Exclusive time %": 0.014793,
      "Inclusive time %": 0.014793,
      "exclusive_time_rank_avg": 0.179367,
      "exclusive_time_rank_max": 0.200584,
      "exclusive_time_rank_min": 0.157931,
      "inclusive_time_rank_avg": 0.179367,
      "inclusive_time_rank_max": 0.200584,
      "inclusive_time_rank_min": 0.157931
    },
    {
      "path": "main/simulation/timestep/state-update/state-hd",
      "Exclusive time %": 0.552513,
      "Inclusive time %": 0.552513,
      "exclusive_time_rank_avg": 6.699461,
      "exclusive_time_rank_max": 6.921624,
      "exclusive_time_rank_min": 6.217172,
      "inclusive_time_rank_avg": 6.699461,
      "inclusive_time_rank_max": 6.921624,
      "inclusive_time_rank_min": 6.217172
    },
    {
      "path": "main/simulation/timestep/setup-tree-matrix/cur-kBK",
      "Exclusive time %": 1.462346,
      "Inclusive time %": 1.462346,
      "exclusive_time_rank_avg": 17.731599,
      "exclusive_time_rank_max": 18.352563,
      "exclusive_time_rank_min": 16.809217,
      "inclusive_time_rank_avg": 17.731599,
      "inclusive_time_rank_max": 18.352563,
      "inclusive_time_rank_min": 16.809217
    },
    {
      "path": "main/simulation/timestep/update",
      "Exclusive time %": 0.323182,
      "Inclusive time %": 0.323182,
      "exclusive_time_rank_avg": 3.918725,
      "exclusive_time_rank_max": 4.682053,
      "exclusive_time_rank_min": 3.447132,
      "inclusive_time_rank_avg": 3.918725,
      "inclusive_time_rank_max": 4.682053,
      "inclusive_time_rank_min": 3.447132
    },
    {
      "path": "main/simulation/timestep/state-update/state-ch_KCaS",
      "Exclusive time %": 0.012724,
      "Inclusive time %": 0.012724,
      "exclusive_time_rank_avg": 0.154281,
      "exclusive_time_rank_max": 0.180436,
      "exclusive_time_rank_min": 0.118686,
      "inclusive_time_rank_avg": 0.154281,
      "inclusive_time_rank_max": 0.180436,
      "inclusive_time_rank_min": 0.118686
    },
    {
      "path": "main/finitialize/cur-cal",
      "Exclusive time %": 3.7e-05,
      "Inclusive time %": 3.7e-05,
      "exclusive_time_rank_avg": 0.000449,
      "exclusive_time_rank_max": 0.000509,
      "exclusive_time_rank_min": 0.000327,
      "inclusive_time_rank_avg": 0.000449,
      "inclusive_time_rank_max": 0.000509,
      "inclusive_time_rank_min": 0.000327
    },
    {
      "path": "main/finitialize/cur-kctin",
      "Exclusive time %": 1e-06,
      "Inclusive time %": 1e-06,
      "exclusive_time_rank_avg": 1.2e-05,
      "exclusive_time_rank_max": 3.4e-05,
      "exclusive_time_rank_min": 8e-06,
      "inclusive_time_rank_avg": 1.2e-05,
      "inclusive_time_rank_max": 3.4e-05,
      "inclusive_time_rank_min": 8e-06
    },
    {
      "path": "main/output-spike/MPI_File_close",
      "Exclusive time %": 0.00246,
      "Inclusive time %": 0.00246,
      "exclusive_time_rank_avg": 0.029825,
      "exclusive_time_rank_max": 0.053654,
      "exclusive_time_rank_min": 0.000878,
      "inclusive_time_rank_avg": 0.029825,
      "inclusive_time_rank_max": 0.053654,
      "inclusive_time_rank_min": 0.000878
    },
    {
      "path": "main/simulation/timestep/deliver-events/net-buf-receive-MyExp2SynBB",
      "Exclusive time %": 0.020577,
      "Inclusive time %": 0.020577,
      "exclusive_time_rank_avg": 0.249503,
      "exclusive_time_rank_max": 0.268324,
      "exclusive_time_rank_min": 0.232521,
      "inclusive_time_rank_avg": 0.249503,
      "inclusive_time_rank_max": 0.268324,
      "inclusive_time_rank_min": 0.232521
    },
    {
      "path": "main/simulation/spike-exchange/spike-exchange/communication/MPI_Allgatherv",
      "Exclusive time %": 0.004032,
      "Inclusive time %": 0.004032,
      "exclusive_time_rank_avg": 0.048894,
      "exclusive_time_rank_max": 0.051212,
      "exclusive_time_rank_min": 0.046375,
      "inclusive_time_rank_avg": 0.048894,
      "inclusive_time_rank_max": 0.051212,
      "inclusive_time_rank_min": 0.046375
    },
    {
      "path": "main/simulation/timestep/state-update/state-ch_Kdrfastngf",
      "Exclusive time %": 0.019209,
      "Inclusive time %": 0.019209,
      "exclusive_time_rank_avg": 0.232916,
      "exclusive_time_rank_max": 0.269409,
      "exclusive_time_rank_min": 0.20563,
      "inclusive_time_rank_avg": 0.232916,
      "inclusive_time_rank_max": 0.269409,
      "inclusive_time_rank_min": 0.20563
    },
    {
      "path": "main/simulation/timestep/setup-tree-matrix/cur-cal",
      "Exclusive time %": 1.759898,
      "Inclusive time %": 1.759898,
      "exclusive_time_rank_avg": 21.339552,
      "exclusive_time_rank_max": 22.23302,
      "exclusive_time_rank_min": 20.206125,
      "inclusive_time_rank_avg": 21.339552,
      "inclusive_time_rank_max": 22.23302,
      "inclusive_time_rank_min": 20.206125
    },
    {
      "path": "main/simulation/timestep/state-update/state-ican",
      "Exclusive time %": 0.012809,
      "Inclusive time %": 0.012809,
      "exclusive_time_rank_avg": 0.155318,
      "exclusive_time_rank_max": 0.18081,
      "exclusive_time_rank_min": 0.140846,
      "inclusive_time_rank_avg": 0.155318,
      "inclusive_time_rank_max": 0.18081,
      "inclusive_time_rank_min": 0.140846
    },
    {
      "path": "main/simulation/timestep/setup-tree-matrix/cur-kctin",
      "Exclusive time %": 0.021063,
      "Inclusive time %": 0.021063,
      "exclusive_time_rank_avg": 0.255394,
      "exclusive_time_rank_max": 0.28659,
      "exclusive_time_rank_min": 0.232869,
      "inclusive_time_rank_avg": 0.255394,
      "inclusive_time_rank_max": 0.28659,
      "inclusive_time_rank_min": 0.232869
    },
    {
      "path": "main/finitialize/cur-cancr",
      "Exclusive time %": 1e-06,
      "Inclusive time %": 1e-06,
      "exclusive_time_rank_avg": 1.4e-05,
      "exclusive_time_rank_max": 4.9e-05,
      "exclusive_time_rank_min": 8e-06,
      "inclusive_time_rank_avg": 1.4e-05,
      "inclusive_time_rank_max": 4.9e-05,
      "inclusive_time_rank_min": 8e-06
    },
    {
      "path": "main/simulation/timestep/deliver-events/net-buf-receive-MyExp2SynNMDABB",
      "Exclusive time %": 0.01839,
      "Inclusive time %": 0.01839,
      "exclusive_time_rank_avg": 0.222983,
      "exclusive_time_rank_max": 0.239569,
      "exclusive_time_rank_min": 0.202043,
      "inclusive_time_rank_avg": 0.222983,
      "inclusive_time_rank_max": 0.239569,
      "inclusive_time_rank_min": 0.202043
    },
    {
      "path": "main/simulation/timestep/setup-tree-matrix/cur-cancr",
      "Exclusive time %": 0.025709,
      "Inclusive time %": 0.025709,
      "exclusive_time_rank_avg": 0.311736,
      "exclusive_time_rank_max": 0.36441,
      "exclusive_time_rank_min": 0.281335,
      "inclusive_time_rank_avg": 0.311736,
      "inclusive_time_rank_max": 0.36441,
      "inclusive_time_rank_min": 0.281335
    },
    {
      "path": "main/simulation/timestep/state-update/state-iCcr",
      "Exclusive time %": 0.016532,
      "Inclusive time %": 0.016532,
      "exclusive_time_rank_avg": 0.200459,
      "exclusive_time_rank_max": 0.225765,
      "exclusive_time_rank_min": 0.169712,
      "inclusive_time_rank_avg": 0.200459,
      "inclusive_time_rank_max": 0.225765,
      "inclusive_time_rank_min": 0.169712
    },
    {
      "path": "main/finitialize/cur-canin",
      "Exclusive time %": 1e-06,
      "Inclusive time %": 1e-06,
      "exclusive_time_rank_avg": 8e-06,
      "exclusive_time_rank_max": 4.2e-05,
      "exclusive_time_rank_min": 4e-06,
      "inclusive_time_rank_avg": 8e-06,
      "inclusive_time_rank_max": 4.2e-05,
      "inclusive_time_rank_min": 4e-06
    },
    {
      "path": "main/simulation/timestep/deliver-events/net-buf-receive-Exp2Syn",
      "Exclusive time %": 0.013274,
      "Inclusive time %": 0.013274,
      "exclusive_time_rank_avg": 0.160948,
      "exclusive_time_rank_max": 0.183451,
      "exclusive_time_rank_min": 0.136818,
      "inclusive_time_rank_avg": 0.160948,
      "inclusive_time_rank_max": 0.183451,
      "inclusive_time_rank_min": 0.136818
    },
    {
      "path": "main/simulation/timestep/setup-tree-matrix/cur-canin",
      "Exclusive time %": 0.018032,
      "Inclusive time %": 0.018032,
      "exclusive_time_rank_avg": 0.218647,
      "exclusive_time_rank_max": 0.248115,
      "exclusive_time_rank_min": 0.193995,
      "inclusive_time_rank_avg": 0.218647,
      "inclusive_time_rank_max": 0.248115,
      "inclusive_time_rank_min": 0.193995
    },
    {
      "path": "main/simulation/timestep/state-update/state-IKscr",
      "Exclusive time %": 0.012224,
      "Inclusive time %": 0.012224,
      "exclusive_time_rank_avg": 0.148216,
      "exclusive_time_rank_max": 0.171985,
      "exclusive_time_rank_min": 0.131292,
      "inclusive_time_rank_avg": 0.148216,
      "inclusive_time_rank_max": 0.171985,
      "inclusive_time_rank_min": 0.131292
    },
    {
      "path": "main/finitialize/cur-can",
      "Exclusive time %": 3.4e-05,
      "Inclusive time %": 3.4e-05,
      "exclusive_time_rank_avg": 0.000412,
      "exclusive_time_rank_max": 0.000464,
      "exclusive_time_rank_min": 0.00035,
      "inclusive_time_rank_avg": 0.000412,
      "inclusive_time_rank_max": 0.000464,
      "inclusive_time_rank_min": 0.00035
    },
    {
      "path": "main/simulation/timestep/deliver-events/net-buf-receive-ExpSyn",
      "Exclusive time %": 0.012788,
      "Inclusive time %": 0.012788,
      "exclusive_time_rank_avg": 0.155061,
      "exclusive_time_rank_max": 0.170222,
      "exclusive_time_rank_min": 0.140599,
      "inclusive_time_rank_avg": 0.155061,
      "inclusive_time_rank_max": 0.170222,
      "inclusive_time_rank_min": 0.140599
    },
    {
      "path": "main/simulation/timestep/setup-tree-matrix/cur-can",
      "Exclusive time %": 1.694756,
      "Inclusive time %": 1.694756,
      "exclusive_time_rank_avg": 20.549669,
      "exclusive_time_rank_max": 21.593779,
      "exclusive_time_rank_min": 19.295539,
      "inclusive_time_rank_avg": 20.549669,
      "inclusive_time_rank_max": 21.593779,
      "inclusive_time_rank_min": 19.295539
    },
    {
      "path": "main/simulation/timestep/state-update/state-IKsin",
      "Exclusive time %": 0.014718,
      "Inclusive time %": 0.014718,
      "exclusive_time_rank_avg": 0.178458,
      "exclusive_time_rank_max": 0.221892,
      "exclusive_time_rank_min": 0.139622,
      "inclusive_time_rank_avg": 0.178458,
      "inclusive_time_rank_max": 0.221892,
      "inclusive_time_rank_min": 0.139622
    },
    {
      "path": "main/finitialize/cur-cat",
      "Exclusive time %": 3e-06,
      "Inclusive time %": 3e-06,
      "exclusive_time_rank_avg": 3.8e-05,
      "exclusive_time_rank_max": 8.6e-05,
      "exclusive_time_rank_min": 2.3e-05,
      "inclusive_time_rank_avg": 3.8e-05,
      "inclusive_time_rank_max": 8.6e-05,
      "inclusive_time_rank_min": 2.3e-05
    },
    {
      "path": "main/simulation/timestep/deliver-events/net-buf-receive-GABAB",
      "Exclusive time %": 0.012083,
      "Inclusive time %": 0.012083,
      "exclusive_time_rank_avg": 0.146509,
      "exclusive_time_rank_max": 0.16189,
      "exclusive_time_rank_min": 0.128263,
      "inclusive_time_rank_avg": 0.146509,
      "inclusive_time_rank_max": 0.16189,
      "inclusive_time_rank_min": 0.128263
    },
    {
      "path": "main/simulation/timestep/setup-tree-matrix/cur-cat",
      "Exclusive time %": 0.109445,
      "Inclusive time %": 0.109445,
      "exclusive_time_rank_avg": 1.32707,
      "exclusive_time_rank_max": 1.4493,
      "exclusive_time_rank_min": 1.172829,
      "inclusive_time_rank_avg": 1.32707,
      "inclusive_time_rank_max": 1.4493,
      "inclusive_time_rank_min": 1.172829
    },
    {
      "path": "main/simulation/timestep/state-update/state-kap",
      "Exclusive time %": 1.614707,
      "Inclusive time %": 1.614707,
      "exclusive_time_rank_avg": 19.57904,
      "exclusive_time_rank_max": 20.748214,
      "exclusive_time_rank_min": 18.368611,
      "inclusive_time_rank_avg": 19.57904,
      "inclusive_time_rank_max": 20.748214,
      "inclusive_time_rank_min": 18.368611
    },
    {
      "path": "main/finitialize/cur-ch_CavL",
      "Exclusive time %": 1e-06,
      "Inclusive time %": 1e-06,
      "exclusive_time_rank_avg": 8e-06,
      "exclusive_time_rank_max": 2.8e-05,
      "exclusive_time_rank_min": 5e-06,
      "inclusive_time_rank_avg": 8e-06,
      "inclusive_time_rank_max": 2.8e-05,
      "inclusive_time_rank_min": 5e-06
    },
    {
      "path": "main/simulation/timestep/deliver-events/net-buf-receive-MyExp2Syn",
      "Exclusive time %": 0.011685,
      "Inclusive time %": 0.011685,
      "exclusive_time_rank_avg": 0.141689,
      "exclusive_time_rank_max": 0.161191,
      "exclusive_time_rank_min": 0.128565,
      "inclusive_time_rank_avg": 0.141689,
      "inclusive_time_rank_max": 0.161191,
      "inclusive_time_rank_min": 0.128565
    },
    {
      "path": "main/simulation/timestep/setup-tree-matrix/cur-ch_CavL",
      "Exclusive time %": 0.0224,
      "Inclusive time %": 0.0224,
      "exclusive_time_rank_avg": 0.271608,
      "exclusive_time_rank_max": 0.316485,
      "exclusive_time_rank_min": 0.2266,
      "inclusive_time_rank_avg": 0.271608,
      "inclusive_time_rank_max": 0.316485,
      "inclusive_time_rank_min": 0.2266
    },
    {
      "path": "main/simulation/timestep/state-update/state-kapcb",
      "Exclusive time %": 0.026805,
      "Inclusive time %": 0.026805,
      "exclusive_time_rank_avg": 0.325021,
      "exclusive_time_rank_max": 0.357356,
      "exclusive_time_rank_min": 0.303629,
      "inclusive_time_rank_avg": 0.325021,
      "inclusive_time_rank_max": 0.357356,
      "inclusive_time_rank_min": 0.303629
    },
    {
      "path": "main/finitialize/cur-ch_CavN",
      "Exclusive time %": 0,
      "Inclusive time %": 0,
      "exclusive_time_rank_avg": 3e-06,
      "exclusive_time_rank_max": 6e-06,
      "exclusive_time_rank_min": 2e-06,
      "inclusive_time_rank_avg": 3e-06,
      "inclusive_time_rank_max": 6e-06,
      "inclusive_time_rank_min": 2e-06
    },
    {
      "path": "main/simulation/timestep/setup-tree-matrix/cur-ch_CavN",
      "Exclusive time %": 0.016817,
      "Inclusive time %": 0.016817,
      "exclusive_time_rank_avg": 0.203916,
      "exclusive_time_rank_max": 0.238557,
      "exclusive_time_rank_min": 0.170215,
      "inclusive_time_rank_avg": 0.203916,
      "inclusive_time_rank_max": 0.238557,
      "inclusive_time_rank_min": 0.170215
    },
    {
      "path": "main/simulation/timestep/state-update/state-kapin",
      "Exclusive time %": 0.019337,
      "Inclusive time %": 0.019337,
      "exclusive_time_rank_avg": 0.234475,
      "exclusive_time_rank_max": 0.27927,
      "exclusive_time_rank_min": 0.19873,
      "inclusive_time_rank_avg": 0.234475,
      "inclusive_time_rank_max": 0.27927,
      "inclusive_time_rank_min": 0.19873
    },
    {
      "path": "main/finitialize/cur-kdmc",
      "Exclusive time %": 2e-06,
      "Inclusive time %": 2e-06,
      "exclusive_time_rank_avg": 1.8e-05,
      "exclusive_time_rank_max": 2.6e-05,
      "exclusive_time_rank_min": 1.2e-05,
      "inclusive_time_rank_avg": 1.8e-05,
      "inclusive_time_rank_max": 2.6e-05,
      "inclusive_time_rank_min": 1.2e-05
    },
    {
      "path": "main/finitialize/cur-ch_KCaS",
      "Exclusive time %": 0,
      "Inclusive time %": 0,
      "exclusive_time_rank_avg": 4e-06,
      "exclusive_time_rank_max": 1.2e-05,
      "exclusive_time_rank_min": 2e-06,
      "inclusive_time_rank_avg": 4e-06,
      "inclusive_time_rank_max": 1.2e-05,
      "inclusive_time_rank_min": 2e-06
    },
    {
      "path": "main/simulation/timestep/state-update/state-iconc_Ca",
      "Exclusive time %": 0.056252,
      "Inclusive time %": 0.056252,
      "exclusive_time_rank_avg": 0.682086,
      "exclusive_time_rank_max": 0.791689,
      "exclusive_time_rank_min": 0.602183,
      "inclusive_time_rank_avg": 0.682086,
      "inclusive_time_rank_max": 0.791689,
      "inclusive_time_rank_min": 0.602183
    }
  ],
  "neurodamus_version": "netpyne-m-one/0.1-20211206",
  "backend": "cpu-nmodl",
  "coreneuron_input": "/gpfs/bbp.cscs.ch/home/magkanar/proj16scratch/FRONTIERS/neuron-frontiers-2021/netpyne/M1/run_coreneuron_simulation/../generate_coreneuron_input/coredat_80/coredat",
  "output_directory": "/gpfs/bbp.cscs.ch/home/magkanar/proj16scratch/FRONTIERS/neuron-frontiers-2021/netpyne/M1/run_coreneuron_simulation/159816-cpu-nmodl",
  "gpus_per_node": "0",
  "env": {
    "SLURM_CLUSTER_NAME": "ps",
    "SLURM_CONF": "/etc/slurm/slurm.conf",
    "SLURM_CPUS_ON_NODE": "80",
    "SLURM_CPUS_PER_TASK": "2",
    "SLURM_GTIDS": "0",
    "SLURM_JOBID": "159816",
    "SLURM_JOB_ACCOUNT": "proj16",
    "SLURM_JOB_CPUS_PER_NODE": "80(x2)",
    "SLURM_JOB_GID": "10067",
    "SLURM_JOB_ID": "159816",
    "SLURM_JOB_NAME": "run_coreneuron_sim.sh",
    "SLURM_JOB_NODELIST": "r5i2n[7,9]",
    "SLURM_JOB_NUM_NODES": "2",
    "SLURM_JOB_PARTITION": "prod",
    "SLURM_JOB_QOS": "normal",
    "SLURM_JOB_UID": "195996",
    "SLURM_JOB_USER": "magkanar",
    "SLURM_KILL_BAD_EXIT": "1",
    "SLURM_LOCALID": "0",
    "SLURM_MEM_PER_NODE": "385246",
    "SLURM_NNODES": "2",
    "SLURM_NODEID": "0",
    "SLURM_NODELIST": "r5i2n[7,9]",
    "SLURM_NODE_ALIASES": "(null)",
    "SLURM_NPROCS": "80",
    "SLURM_NTASKS": "80",
    "SLURM_PRIO_PROCESS": "0",
    "SLURM_PROCID": "0",
    "SLURM_SPANK_AUKS": "no",
    "SLURM_SUBMIT_DIR": "/gpfs/bbp.cscs.ch/data/scratch/proj16/magkanar/FRONTIERS/neuron-frontiers-2021/netpyne/M1/run_coreneuron_simulation",
    "SLURM_SUBMIT_HOST": "bbpv1.epfl.ch",
    "SLURM_TASKS_PER_NODE": "40(x2)",
    "SLURM_TASK_PID": "239759",
    "SLURM_TIME_FORMAT": "relative",
    "SLURM_TOPOLOGY_ADDR": "ibsw69.ibsw50.ibsw4.r5i2n7",
    "SLURM_TOPOLOGY_ADDR_PATTERN": "switch.switch.switch.node",
    "SLURM_WORKING_CLUSTER": "ps:bbpv1:6810:9472:101",
    "CALI_CHANNEL_FLUSH_ON_EXIT": "false",
    "CALI_MPIREPORT_CONFIG": "SELECT annotation, mpi.function, min(sum#sum#time.duration) as \"exclusive_time_rank_min\", max(sum#sum#time.duration) as \"exclusive_time_rank_max\", avg(sum#sum#time.duration) as \"exclusive_time_rank_avg\", min(inclusive#sum#time.duration) AS \"inclusive_time_rank_min\", max(inclusive#sum#time.duration) AS \"inclusive_time_rank_max\", avg(inclusive#sum#time.duration) AS \"inclusive_time_rank_avg\", percent_total(sum#sum#time.duration) AS \"Exclusive time %\", inclusive_percent_total(sum#sum#time.duration) AS \"Inclusive time %\" GROUP BY prop:nested FORMAT json",
    "CALI_MPIREPORT_FILENAME": "caliper.json",
    "CALI_MPIREPORT_LOCAL_CONFIG": "SELECT sum(sum#time.duration), inclusive_sum(sum#time.duration) GROUP BY prop:nested",
    "CALI_MPI_BLACKLIST": "MPI_Comm_rank,MPI_Comm_size,MPI_Wtick,MPI_Wtime",
    "CALI_SERVICES_ENABLE": "aggregate,event,mpi,mpireport,nvtx,timestamp"
  }
}
