{
  "data": [
    {
      "Exclusive time %": 0.000137,
      "Inclusive time %": 0.000137,
      "exclusive_time_rank_avg": 0.0003,
      "exclusive_time_rank_max": 0.00041,
      "exclusive_time_rank_min": 0.000284,
      "inclusive_time_rank_avg": 0.0003,
      "inclusive_time_rank_max": 0.00041,
      "inclusive_time_rank_min": 0.000284
    },
    {
      "path": "main",
      "Exclusive time %": 0.932106,
      "Inclusive time %": 99.999863,
      "exclusive_time_rank_avg": 2.045968,
      "exclusive_time_rank_max": 2.124321,
      "exclusive_time_rank_min": 1.956091,
      "inclusive_time_rank_avg": 219.499079,
      "inclusive_time_rank_max": 219.633387,
      "inclusive_time_rank_min": 219.471919
    },
    {
      "path": "main/load-model",
      "Exclusive time %": 6.075514,
      "Inclusive time %": 6.353448,
      "exclusive_time_rank_avg": 13.335716,
      "exclusive_time_rank_max": 13.977538,
      "exclusive_time_rank_min": 12.572942,
      "inclusive_time_rank_avg": 13.94578,
      "inclusive_time_rank_max": 14.000786,
      "inclusive_time_rank_min": 13.791261
    },
    {
      "path": "main/output-spike",
      "Exclusive time %": 0.00049,
      "Inclusive time %": 0.082737,
      "exclusive_time_rank_avg": 0.001076,
      "exclusive_time_rank_max": 0.001395,
      "exclusive_time_rank_min": 0.000714,
      "inclusive_time_rank_avg": 0.181607,
      "inclusive_time_rank_max": 0.182818,
      "inclusive_time_rank_min": 0.180229
    },
    {
      "path": "main/MPI_Allreduce",
      "Exclusive time %": 0.042862,
      "Inclusive time %": 0.042862,
      "exclusive_time_rank_avg": 0.094081,
      "exclusive_time_rank_max": 0.235441,
      "exclusive_time_rank_min": 0.005957,
      "inclusive_time_rank_avg": 0.094081,
      "inclusive_time_rank_max": 0.235441,
      "inclusive_time_rank_min": 0.005957
    },
    {
      "path": "main/load-model/MPI_Allreduce",
      "Exclusive time %": 0.277934,
      "Inclusive time %": 0.277934,
      "exclusive_time_rank_avg": 0.610064,
      "exclusive_time_rank_max": 1.375285,
      "exclusive_time_rank_min": 0.016328,
      "inclusive_time_rank_avg": 0.610064,
      "inclusive_time_rank_max": 1.375285,
      "inclusive_time_rank_min": 0.016328
    },
    {
      "path": "main/output-spike/MPI_Allreduce",
      "Exclusive time %": 6.6e-05,
      "Inclusive time %": 6.6e-05,
      "exclusive_time_rank_avg": 0.000145,
      "exclusive_time_rank_max": 0.000306,
      "exclusive_time_rank_min": 3e-05,
      "inclusive_time_rank_avg": 0.000145,
      "inclusive_time_rank_max": 0.000306,
      "inclusive_time_rank_min": 3e-05
    },
    {
      "path": "main/simulation",
      "Exclusive time %": 0.004852,
      "Inclusive time %": 40.286786,
      "exclusive_time_rank_avg": 0.010649,
      "exclusive_time_rank_max": 0.012919,
      "exclusive_time_rank_min": 0.010301,
      "inclusive_time_rank_avg": 88.429245,
      "inclusive_time_rank_max": 88.435721,
      "inclusive_time_rank_min": 88.423745
    },
    {
      "path": "main/simulation/spike-exchange",
      "Exclusive time %": 0.021034,
      "Inclusive time %": 2.297493,
      "exclusive_time_rank_avg": 0.04617,
      "exclusive_time_rank_max": 0.048603,
      "exclusive_time_rank_min": 0.043928,
      "inclusive_time_rank_avg": 5.042983,
      "inclusive_time_rank_max": 6.238256,
      "inclusive_time_rank_min": 3.707975
    },
    {
      "path": "main/simulation/spike-exchange/imbalance",
      "Exclusive time %": 0.002151,
      "Inclusive time %": 2.234971,
      "exclusive_time_rank_avg": 0.004722,
      "exclusive_time_rank_max": 0.005284,
      "exclusive_time_rank_min": 0.004523,
      "inclusive_time_rank_avg": 4.905748,
      "inclusive_time_rank_max": 6.106936,
      "inclusive_time_rank_min": 3.568515
    },
    {
      "path": "main/finitialize",
      "Exclusive time %": 51.279336,
      "Inclusive time %": 52.157003,
      "exclusive_time_rank_avg": 112.557824,
      "exclusive_time_rank_max": 114.479724,
      "exclusive_time_rank_min": 109.556362,
      "inclusive_time_rank_avg": 114.484299,
      "inclusive_time_rank_max": 114.503561,
      "inclusive_time_rank_min": 114.478212
    },
    {
      "path": "main/finitialize/spike-exchange",
      "Exclusive time %": 4e-06,
      "Inclusive time %": 0.87747,
      "exclusive_time_rank_avg": 8e-06,
      "exclusive_time_rank_max": 1.2e-05,
      "exclusive_time_rank_min": 6e-06,
      "inclusive_time_rank_avg": 1.926041,
      "inclusive_time_rank_max": 4.924445,
      "inclusive_time_rank_min": 0.000447
    },
    {
      "path": "main/finitialize/spike-exchange/imbalance",
      "Exclusive time %": 4e-06,
      "Inclusive time %": 0.877284,
      "exclusive_time_rank_avg": 9e-06,
      "exclusive_time_rank_max": 1.7e-05,
      "exclusive_time_rank_min": 5e-06,
      "inclusive_time_rank_avg": 1.925633,
      "inclusive_time_rank_max": 4.924061,
      "inclusive_time_rank_min": 2.4e-05
    },
    {
      "path": "main/MPI_Barrier",
      "Exclusive time %": 0.024625,
      "Inclusive time %": 0.024625,
      "exclusive_time_rank_avg": 0.054051,
      "exclusive_time_rank_max": 0.208064,
      "exclusive_time_rank_min": 0.000101,
      "inclusive_time_rank_avg": 0.054051,
      "inclusive_time_rank_max": 0.208064,
      "inclusive_time_rank_min": 0.000101
    },
    {
      "path": "main/simulation/spike-exchange/imbalance/MPI_Barrier",
      "Exclusive time %": 2.23282,
      "Inclusive time %": 2.23282,
      "exclusive_time_rank_avg": 4.901026,
      "exclusive_time_rank_max": 6.102291,
      "exclusive_time_rank_min": 3.563656,
      "inclusive_time_rank_avg": 4.901026,
      "inclusive_time_rank_max": 6.102291,
      "inclusive_time_rank_min": 3.563656
    },
    {
      "path": "main/simulation/MPI_Barrier",
      "Exclusive time %": 5e-06,
      "Inclusive time %": 5e-06,
      "exclusive_time_rank_avg": 1.1e-05,
      "exclusive_time_rank_max": 1.4e-05,
      "exclusive_time_rank_min": 7e-06,
      "inclusive_time_rank_avg": 1.1e-05,
      "inclusive_time_rank_max": 1.4e-05,
      "inclusive_time_rank_min": 7e-06
    },
    {
      "path": "main/output-spike/MPI_Barrier",
      "Exclusive time %": 4.6e-05,
      "Inclusive time %": 4.6e-05,
      "exclusive_time_rank_avg": 0.000101,
      "exclusive_time_rank_max": 0.000264,
      "exclusive_time_rank_min": 9e-06,
      "inclusive_time_rank_avg": 0.000101,
      "inclusive_time_rank_max": 0.000264,
      "inclusive_time_rank_min": 9e-06
    },
    {
      "path": "main/finitialize/spike-exchange/imbalance/MPI_Barrier",
      "Exclusive time %": 0.87728,
      "Inclusive time %": 0.87728,
      "exclusive_time_rank_avg": 1.925624,
      "exclusive_time_rank_max": 4.92405,
      "exclusive_time_rank_min": 1.8e-05,
      "inclusive_time_rank_avg": 1.925624,
      "inclusive_time_rank_max": 4.92405,
      "inclusive_time_rank_min": 1.8e-05
    },
    {
      "path": "main/simulation/timestep",
      "Exclusive time %": 1.661004,
      "Inclusive time %": 37.984436,
      "exclusive_time_rank_avg": 3.645895,
      "exclusive_time_rank_max": 3.823383,
      "exclusive_time_rank_min": 3.501029,
      "inclusive_time_rank_avg": 83.375602,
      "inclusive_time_rank_max": 84.709816,
      "inclusive_time_rank_min": 82.185443
    },
    {
      "path": "main/simulation/timestep/deliver-events",
      "Exclusive time %": 6.079844,
      "Inclusive time %": 19.161288,
      "exclusive_time_rank_avg": 13.345221,
      "exclusive_time_rank_max": 14.422673,
      "exclusive_time_rank_min": 12.674227,
      "inclusive_time_rank_avg": 42.058907,
      "inclusive_time_rank_max": 42.983154,
      "inclusive_time_rank_min": 41.227889
    },
    {
      "path": "main/handle-forward-skip",
      "Exclusive time %": 0.000104,
      "Inclusive time %": 0.101822,
      "exclusive_time_rank_avg": 0.000229,
      "exclusive_time_rank_max": 0.000589,
      "exclusive_time_rank_min": 6.2e-05,
      "inclusive_time_rank_avg": 0.2235,
      "inclusive_time_rank_max": 0.228998,
      "inclusive_time_rank_min": 0.217024
    },
    {
      "path": "main/handle-forward-skip/timestep",
      "Exclusive time %": 0.005093,
      "Inclusive time %": 0.101718,
      "exclusive_time_rank_avg": 0.011179,
      "exclusive_time_rank_max": 0.016695,
      "exclusive_time_rank_min": 0.007112,
      "inclusive_time_rank_avg": 0.223271,
      "inclusive_time_rank_max": 0.228581,
      "inclusive_time_rank_min": 0.216949
    },
    {
      "path": "main/handle-forward-skip/timestep/deliver-events",
      "Exclusive time %": 0.04373,
      "Inclusive time %": 0.049329,
      "exclusive_time_rank_avg": 0.095988,
      "exclusive_time_rank_max": 0.116064,
      "exclusive_time_rank_min": 0.066728,
      "inclusive_time_rank_avg": 0.108276,
      "inclusive_time_rank_max": 0.130516,
      "inclusive_time_rank_min": 0.079675
    },
    {
      "path": "main/finitialize/update-net-receive-buf",
      "Exclusive time %": 1.8e-05,
      "Inclusive time %": 1.8e-05,
      "exclusive_time_rank_avg": 4e-05,
      "exclusive_time_rank_max": 5.9e-05,
      "exclusive_time_rank_min": 3.4e-05,
      "inclusive_time_rank_avg": 4e-05,
      "inclusive_time_rank_max": 5.9e-05,
      "inclusive_time_rank_min": 3.4e-05
    },
    {
      "path": "main/simulation/timestep/deliver-events/update-net-receive-buf",
      "Exclusive time %": 0.021081,
      "Inclusive time %": 11.069822,
      "exclusive_time_rank_avg": 0.046272,
      "exclusive_time_rank_max": 0.051263,
      "exclusive_time_rank_min": 0.044792,
      "inclusive_time_rank_avg": 24.29819,
      "inclusive_time_rank_max": 24.8631,
      "inclusive_time_rank_min": 23.51471
    },
    {
      "path": "main/handle-forward-skip/timestep/deliver-events/update-net-receive-buf",
      "Exclusive time %": 3.2e-05,
      "Inclusive time %": 3.2e-05,
      "exclusive_time_rank_avg": 7.1e-05,
      "exclusive_time_rank_max": 8e-05,
      "exclusive_time_rank_min": 6.5e-05,
      "inclusive_time_rank_avg": 7.1e-05,
      "inclusive_time_rank_max": 8e-05,
      "inclusive_time_rank_min": 6.5e-05
    },
    {
      "path": "main/simulation/timestep/setup-tree-matrix",
      "Exclusive time %": 0.139411,
      "Inclusive time %": 0.725044,
      "exclusive_time_rank_avg": 0.306006,
      "exclusive_time_rank_max": 0.351507,
      "exclusive_time_rank_min": 0.290269,
      "inclusive_time_rank_avg": 1.591466,
      "inclusive_time_rank_max": 1.788713,
      "inclusive_time_rank_min": 1.528484
    },
    {
      "path": "main/handle-forward-skip/timestep/setup-tree-matrix",
      "Exclusive time %": 0.000341,
      "Inclusive time %": 0.001806,
      "exclusive_time_rank_avg": 0.000748,
      "exclusive_time_rank_max": 0.000938,
      "exclusive_time_rank_min": 0.000658,
      "inclusive_time_rank_avg": 0.003963,
      "inclusive_time_rank_max": 0.004472,
      "inclusive_time_rank_min": 0.003456
    },
    {
      "path": "main/finitialize/cur-pas",
      "Exclusive time %": 9e-06,
      "Inclusive time %": 9e-06,
      "exclusive_time_rank_avg": 2e-05,
      "exclusive_time_rank_max": 3.9e-05,
      "exclusive_time_rank_min": 1.6e-05,
      "inclusive_time_rank_avg": 2e-05,
      "inclusive_time_rank_max": 3.9e-05,
      "inclusive_time_rank_min": 1.6e-05
    },
    {
      "path": "main/output-spike/MPI_Alltoallv",
      "Exclusive time %": 0.000101,
      "Inclusive time %": 0.000101,
      "exclusive_time_rank_avg": 0.000221,
      "exclusive_time_rank_max": 0.000353,
      "exclusive_time_rank_min": 0.000103,
      "inclusive_time_rank_avg": 0.000221,
      "inclusive_time_rank_max": 0.000353,
      "inclusive_time_rank_min": 0.000103
    },
    {
      "path": "main/handle-forward-skip/timestep/deliver-events/net-buf-receive-GluSynapse",
      "Exclusive time %": 1.1e-05,
      "Inclusive time %": 1.1e-05,
      "exclusive_time_rank_avg": 2.5e-05,
      "exclusive_time_rank_max": 3.8e-05,
      "exclusive_time_rank_min": 2.1e-05,
      "inclusive_time_rank_avg": 2.5e-05,
      "inclusive_time_rank_max": 3.8e-05,
      "inclusive_time_rank_min": 2.1e-05
    },
    {
      "path": "main/simulation/timestep/setup-tree-matrix/cur-pas",
      "Exclusive time %": 0.02993,
      "Inclusive time %": 0.02993,
      "exclusive_time_rank_avg": 0.065697,
      "exclusive_time_rank_max": 0.07203,
      "exclusive_time_rank_min": 0.062115,
      "inclusive_time_rank_avg": 0.065697,
      "inclusive_time_rank_max": 0.07203,
      "inclusive_time_rank_min": 0.062115
    },
    {
      "path": "main/handle-forward-skip/timestep/setup-tree-matrix/cur-pas",
      "Exclusive time %": 7e-05,
      "Inclusive time %": 7e-05,
      "exclusive_time_rank_avg": 0.000154,
      "exclusive_time_rank_max": 0.000292,
      "exclusive_time_rank_min": 0.000124,
      "inclusive_time_rank_avg": 0.000154,
      "inclusive_time_rank_max": 0.000292,
      "inclusive_time_rank_min": 0.000124
    },
    {
      "path": "main/handle-forward-skip/timestep/setup-tree-matrix/cur-kca",
      "Exclusive time %": 7.2e-05,
      "Inclusive time %": 7.2e-05,
      "exclusive_time_rank_avg": 0.000158,
      "exclusive_time_rank_max": 0.00034,
      "exclusive_time_rank_min": 0.00013,
      "inclusive_time_rank_avg": 0.000158,
      "inclusive_time_rank_max": 0.00034,
      "inclusive_time_rank_min": 0.00013
    },
    {
      "path": "main/simulation/timestep/deliver-events/net-buf-receive-GluSynapse",
      "Exclusive time %": 0.004781,
      "Inclusive time %": 0.004781,
      "exclusive_time_rank_avg": 0.010495,
      "exclusive_time_rank_max": 0.011128,
      "exclusive_time_rank_min": 0.010165,
      "inclusive_time_rank_avg": 0.010495,
      "inclusive_time_rank_max": 0.011128,
      "inclusive_time_rank_min": 0.010165
    },
    {
      "path": "main/finitialize/cur-na_ion",
      "Exclusive time %": 9e-06,
      "Inclusive time %": 9e-06,
      "exclusive_time_rank_avg": 1.9e-05,
      "exclusive_time_rank_max": 0.000124,
      "exclusive_time_rank_min": 1.4e-05,
      "inclusive_time_rank_avg": 1.9e-05,
      "inclusive_time_rank_max": 0.000124,
      "inclusive_time_rank_min": 1.4e-05
    },
    {
      "path": "main/simulation/timestep/setup-tree-matrix/cur-kca",
      "Exclusive time %": 0.028004,
      "Inclusive time %": 0.028004,
      "exclusive_time_rank_avg": 0.061469,
      "exclusive_time_rank_max": 0.068454,
      "exclusive_time_rank_min": 0.058344,
      "inclusive_time_rank_avg": 0.061469,
      "inclusive_time_rank_max": 0.068454,
      "inclusive_time_rank_min": 0.058344
    },
    {
      "path": "main/handle-forward-skip/timestep/deliver-events/net-buf-receive-ProbAMPANMDA_EMS",
      "Exclusive time %": 0.001864,
      "Inclusive time %": 0.001864,
      "exclusive_time_rank_avg": 0.004092,
      "exclusive_time_rank_max": 0.006411,
      "exclusive_time_rank_min": 0.002874,
      "inclusive_time_rank_avg": 0.004092,
      "inclusive_time_rank_max": 0.006411,
      "inclusive_time_rank_min": 0.002874
    },
    {
      "path": "main/simulation/timestep/state-update/state-hd",
      "Exclusive time %": 0.02016,
      "Inclusive time %": 0.02016,
      "exclusive_time_rank_avg": 0.04425,
      "exclusive_time_rank_max": 0.051249,
      "exclusive_time_rank_min": 0.042784,
      "inclusive_time_rank_avg": 0.04425,
      "inclusive_time_rank_max": 0.051249,
      "inclusive_time_rank_min": 0.042784
    },
    {
      "path": "main/simulation/timestep/setup-tree-matrix/cur-na_ion",
      "Exclusive time %": 0.026975,
      "Inclusive time %": 0.026975,
      "exclusive_time_rank_avg": 0.05921,
      "exclusive_time_rank_max": 0.065697,
      "exclusive_time_rank_min": 0.056293,
      "inclusive_time_rank_avg": 0.05921,
      "inclusive_time_rank_max": 0.065697,
      "inclusive_time_rank_min": 0.056293
    },
    {
      "path": "main/finitialize/cur-kdb",
      "Exclusive time %": 8e-06,
      "Inclusive time %": 8e-06,
      "exclusive_time_rank_avg": 1.8e-05,
      "exclusive_time_rank_max": 3.4e-05,
      "exclusive_time_rank_min": 1.5e-05,
      "inclusive_time_rank_avg": 1.8e-05,
      "inclusive_time_rank_max": 3.4e-05,
      "inclusive_time_rank_min": 1.5e-05
    },
    {
      "path": "main/simulation/timestep/deliver-events/net-buf-receive-ProbAMPANMDA_EMS",
      "Exclusive time %": 0.657805,
      "Inclusive time %": 0.657805,
      "exclusive_time_rank_avg": 1.443878,
      "exclusive_time_rank_max": 1.486162,
      "exclusive_time_rank_min": 1.365382,
      "inclusive_time_rank_avg": 1.443878,
      "inclusive_time_rank_max": 1.486162,
      "inclusive_time_rank_min": 1.365382
    },
    {
      "path": "main/handle-forward-skip/timestep/setup-tree-matrix/cur-na_ion",
      "Exclusive time %": 6.5e-05,
      "Inclusive time %": 6.5e-05,
      "exclusive_time_rank_avg": 0.000143,
      "exclusive_time_rank_max": 0.000626,
      "exclusive_time_rank_min": 0.000113,
      "inclusive_time_rank_avg": 0.000143,
      "inclusive_time_rank_max": 0.000626,
      "inclusive_time_rank_min": 0.000113
    },
    {
      "path": "main/handle-forward-skip/timestep/deliver-events/net-buf-receive-ProbGABAAB_EMS",
      "Exclusive time %": 0.001945,
      "Inclusive time %": 0.001945,
      "exclusive_time_rank_avg": 0.004269,
      "exclusive_time_rank_max": 0.007227,
      "exclusive_time_rank_min": 0.003166,
      "inclusive_time_rank_avg": 0.004269,
      "inclusive_time_rank_max": 0.007227,
      "inclusive_time_rank_min": 0.003166
    },
    {
      "path": "main/finitialize/cur-k_ion",
      "Exclusive time %": 6e-06,
      "Inclusive time %": 6e-06,
      "exclusive_time_rank_avg": 1.3e-05,
      "exclusive_time_rank_max": 0.000131,
      "exclusive_time_rank_min": 1e-05,
      "inclusive_time_rank_avg": 1.3e-05,
      "inclusive_time_rank_max": 0.000131,
      "inclusive_time_rank_min": 1e-05
    },
    {
      "path": "main/handle-forward-skip/timestep/state-update/state-kad",
      "Exclusive time %": 5.5e-05,
      "Inclusive time %": 5.5e-05,
      "exclusive_time_rank_avg": 0.000121,
      "exclusive_time_rank_max": 0.000145,
      "exclusive_time_rank_min": 0.000112,
      "inclusive_time_rank_avg": 0.000121,
      "inclusive_time_rank_max": 0.000145,
      "inclusive_time_rank_min": 0.000112
    },
    {
      "path": "main/simulation/timestep/deliver-events/net-buf-receive-ProbGABAAB_EMS",
      "Exclusive time %": 0.746554,
      "Inclusive time %": 0.746554,
      "exclusive_time_rank_avg": 1.638682,
      "exclusive_time_rank_max": 1.695965,
      "exclusive_time_rank_min": 1.564983,
      "inclusive_time_rank_avg": 1.638682,
      "inclusive_time_rank_max": 1.695965,
      "inclusive_time_rank_min": 1.564983
    },
    {
      "path": "main/simulation/timestep/setup-tree-matrix/cur-k_ion",
      "Exclusive time %": 0.023995,
      "Inclusive time %": 0.023995,
      "exclusive_time_rank_avg": 0.052668,
      "exclusive_time_rank_max": 0.05779,
      "exclusive_time_rank_min": 0.05,
      "inclusive_time_rank_avg": 0.052668,
      "inclusive_time_rank_max": 0.05779,
      "inclusive_time_rank_min": 0.05
    },
    {
      "path": "main/handle-forward-skip/timestep/setup-tree-matrix/cur-kdb",
      "Exclusive time %": 7e-05,
      "Inclusive time %": 7e-05,
      "exclusive_time_rank_avg": 0.000153,
      "exclusive_time_rank_max": 0.000393,
      "exclusive_time_rank_min": 0.000119,
      "inclusive_time_rank_avg": 0.000153,
      "inclusive_time_rank_max": 0.000393,
      "inclusive_time_rank_min": 0.000119
    },
    {
      "path": "main/handle-forward-skip/timestep/deliver-events/net-buf-receive-Exp2Syn",
      "Exclusive time %": 1.2e-05,
      "Inclusive time %": 1.2e-05,
      "exclusive_time_rank_avg": 2.7e-05,
      "exclusive_time_rank_max": 5.9e-05,
      "exclusive_time_rank_min": 2.1e-05,
      "inclusive_time_rank_avg": 2.7e-05,
      "inclusive_time_rank_max": 5.9e-05,
      "inclusive_time_rank_min": 2.1e-05
    },
    {
      "path": "main/handle-forward-skip/timestep/setup-tree-matrix/cur-k_ion",
      "Exclusive time %": 5.6e-05,
      "Inclusive time %": 5.6e-05,
      "exclusive_time_rank_avg": 0.000122,
      "exclusive_time_rank_max": 0.000324,
      "exclusive_time_rank_min": 9.6e-05,
      "inclusive_time_rank_avg": 0.000122,
      "inclusive_time_rank_max": 0.000324,
      "inclusive_time_rank_min": 9.6e-05
    },
    {
      "path": "main/simulation/timestep/setup-tree-matrix/cur-kdb",
      "Exclusive time %": 0.026583,
      "Inclusive time %": 0.026583,
      "exclusive_time_rank_avg": 0.05835,
      "exclusive_time_rank_max": 0.065782,
      "exclusive_time_rank_min": 0.055258,
      "inclusive_time_rank_avg": 0.05835,
      "inclusive_time_rank_max": 0.065782,
      "inclusive_time_rank_min": 0.055258
    },
    {
      "path": "main/finitialize/cur-ca_ion",
      "Exclusive time %": 5e-06,
      "Inclusive time %": 5e-06,
      "exclusive_time_rank_avg": 1.2e-05,
      "exclusive_time_rank_max": 4.1e-05,
      "exclusive_time_rank_min": 9e-06,
      "inclusive_time_rank_avg": 1.2e-05,
      "inclusive_time_rank_max": 4.1e-05,
      "inclusive_time_rank_min": 9e-06
    },
    {
      "path": "main/simulation/timestep/state-update/state-kad",
      "Exclusive time %": 0.021612,
      "Inclusive time %": 0.021612,
      "exclusive_time_rank_avg": 0.047437,
      "exclusive_time_rank_max": 0.055411,
      "exclusive_time_rank_min": 0.045814,
      "inclusive_time_rank_avg": 0.047437,
      "inclusive_time_rank_max": 0.055411,
      "inclusive_time_rank_min": 0.045814
    },
    {
      "path": "main/simulation/timestep/deliver-events/net-buf-receive-Exp2Syn",
      "Exclusive time %": 0.004898,
      "Inclusive time %": 0.004898,
      "exclusive_time_rank_avg": 0.010751,
      "exclusive_time_rank_max": 0.011604,
      "exclusive_time_rank_min": 0.010288,
      "inclusive_time_rank_avg": 0.010751,
      "inclusive_time_rank_max": 0.011604,
      "inclusive_time_rank_min": 0.010288
    },
    {
      "path": "main/output-spike/MPI_Exscan",
      "Exclusive time %": 4.6e-05,
      "Inclusive time %": 4.6e-05,
      "exclusive_time_rank_avg": 0.000102,
      "exclusive_time_rank_max": 0.000252,
      "exclusive_time_rank_min": 2.3e-05,
      "inclusive_time_rank_avg": 0.000102,
      "inclusive_time_rank_max": 0.000252,
      "inclusive_time_rank_min": 2.3e-05
    },
    {
      "path": "main/handle-forward-skip/timestep/deliver-events/net-buf-receive-ExpSyn",
      "Exclusive time %": 1.1e-05,
      "Inclusive time %": 1.1e-05,
      "exclusive_time_rank_avg": 2.5e-05,
      "exclusive_time_rank_max": 4e-05,
      "exclusive_time_rank_min": 2e-05,
      "inclusive_time_rank_avg": 2.5e-05,
      "inclusive_time_rank_max": 4e-05,
      "inclusive_time_rank_min": 2e-05
    },
    {
      "path": "main/simulation/timestep/setup-tree-matrix/cur-ca_ion",
      "Exclusive time %": 0.022863,
      "Inclusive time %": 0.022863,
      "exclusive_time_rank_avg": 0.050185,
      "exclusive_time_rank_max": 0.056351,
      "exclusive_time_rank_min": 0.046222,
      "inclusive_time_rank_avg": 0.050185,
      "inclusive_time_rank_max": 0.056351,
      "inclusive_time_rank_min": 0.046222
    },
    {
      "path": "main/handle-forward-skip/timestep/setup-tree-matrix/cur-ca_ion",
      "Exclusive time %": 5.3e-05,
      "Inclusive time %": 5.3e-05,
      "exclusive_time_rank_avg": 0.000117,
      "exclusive_time_rank_max": 0.000257,
      "exclusive_time_rank_min": 9.1e-05,
      "inclusive_time_rank_avg": 0.000117,
      "inclusive_time_rank_max": 0.000257,
      "inclusive_time_rank_min": 9.1e-05
    },
    {
      "path": "main/finitialize/cur-kdrb",
      "Exclusive time %": 8e-06,
      "Inclusive time %": 8e-06,
      "exclusive_time_rank_avg": 1.8e-05,
      "exclusive_time_rank_max": 4.9e-05,
      "exclusive_time_rank_min": 1.4e-05,
      "inclusive_time_rank_avg": 1.8e-05,
      "inclusive_time_rank_max": 4.9e-05,
      "inclusive_time_rank_min": 1.4e-05
    },
    {
      "path": "main/simulation/timestep/deliver-events/net-buf-receive-ExpSyn",
      "Exclusive time %": 0.004464,
      "Inclusive time %": 0.004464,
      "exclusive_time_rank_avg": 0.009799,
      "exclusive_time_rank_max": 0.010765,
      "exclusive_time_rank_min": 0.009469,
      "inclusive_time_rank_avg": 0.009799,
      "inclusive_time_rank_max": 0.010765,
      "inclusive_time_rank_min": 0.009469
    },
    {
      "path": "main/simulation/spike-exchange/communication",
      "Exclusive time %": 0.002214,
      "Inclusive time %": 0.041488,
      "exclusive_time_rank_avg": 0.00486,
      "exclusive_time_rank_max": 0.005158,
      "exclusive_time_rank_min": 0.004657,
      "inclusive_time_rank_avg": 0.091065,
      "inclusive_time_rank_max": 0.099022,
      "inclusive_time_rank_min": 0.083247
    },
    {
      "path": "main/handle-forward-skip/timestep/state-update/state-kap",
      "Exclusive time %": 5.4e-05,
      "Inclusive time %": 5.4e-05,
      "exclusive_time_rank_avg": 0.000119,
      "exclusive_time_rank_max": 0.000147,
      "exclusive_time_rank_min": 0.000111,
      "inclusive_time_rank_avg": 0.000119,
      "inclusive_time_rank_max": 0.000147,
      "inclusive_time_rank_min": 0.000111
    },
    {
      "path": "main/finitialize/cur-ttx_ion",
      "Exclusive time %": 6e-06,
      "Inclusive time %": 6e-06,
      "exclusive_time_rank_avg": 1.2e-05,
      "exclusive_time_rank_max": 4.4e-05,
      "exclusive_time_rank_min": 9e-06,
      "inclusive_time_rank_avg": 1.2e-05,
      "inclusive_time_rank_max": 4.4e-05,
      "inclusive_time_rank_min": 9e-06
    },
    {
      "path": "main/handle-forward-skip/timestep/setup-tree-matrix/cur-kdrb",
      "Exclusive time %": 6.3e-05,
      "Inclusive time %": 6.3e-05,
      "exclusive_time_rank_avg": 0.000139,
      "exclusive_time_rank_max": 0.000248,
      "exclusive_time_rank_min": 0.00012,
      "inclusive_time_rank_avg": 0.000139,
      "inclusive_time_rank_max": 0.000248,
      "inclusive_time_rank_min": 0.00012
    },
    {
      "path": "main/simulation/timestep/setup-tree-matrix/cur-kdrb",
      "Exclusive time %": 0.026528,
      "Inclusive time %": 0.026528,
      "exclusive_time_rank_avg": 0.058228,
      "exclusive_time_rank_max": 0.06579,
      "exclusive_time_rank_min": 0.055428,
      "inclusive_time_rank_avg": 0.058228,
      "inclusive_time_rank_max": 0.06579,
      "inclusive_time_rank_min": 0.055428
    },
    {
      "path": "main/simulation/timestep/state-update/state-kap",
      "Exclusive time %": 0.02141,
      "Inclusive time %": 0.02141,
      "exclusive_time_rank_avg": 0.046996,
      "exclusive_time_rank_max": 0.054025,
      "exclusive_time_rank_min": 0.045592,
      "inclusive_time_rank_avg": 0.046996,
      "inclusive_time_rank_max": 0.054025,
      "inclusive_time_rank_min": 0.045592
    },
    {
      "path": "main/simulation/timestep/setup-tree-matrix/cur-ttx_ion",
      "Exclusive time %": 0.022419,
      "Inclusive time %": 0.022419,
      "exclusive_time_rank_avg": 0.04921,
      "exclusive_time_rank_max": 0.054872,
      "exclusive_time_rank_min": 0.046104,
      "inclusive_time_rank_avg": 0.04921,
      "inclusive_time_rank_max": 0.054872,
      "inclusive_time_rank_min": 0.046104
    },
    {
      "path": "main/output-spike/MPI_File_open",
      "Exclusive time %": 0.005172,
      "Inclusive time %": 0.005172,
      "exclusive_time_rank_avg": 0.011352,
      "exclusive_time_rank_max": 0.011475,
      "exclusive_time_rank_min": 0.011236,
      "inclusive_time_rank_avg": 0.011352,
      "inclusive_time_rank_max": 0.011475,
      "inclusive_time_rank_min": 0.011236
    },
    {
      "path": "main/handle-forward-skip/timestep/setup-tree-matrix/cur-ttx_ion",
      "Exclusive time %": 5.8e-05,
      "Inclusive time %": 5.8e-05,
      "exclusive_time_rank_avg": 0.000127,
      "exclusive_time_rank_max": 0.000314,
      "exclusive_time_rank_min": 9.3e-05,
      "inclusive_time_rank_avg": 0.000127,
      "inclusive_time_rank_max": 0.000314,
      "inclusive_time_rank_min": 9.3e-05
    },
    {
      "path": "main/handle-forward-skip/timestep/matrix-solver",
      "Exclusive time %": 0.044358,
      "Inclusive time %": 0.044358,
      "exclusive_time_rank_avg": 0.097365,
      "exclusive_time_rank_max": 0.128599,
      "exclusive_time_rank_min": 0.07352,
      "inclusive_time_rank_avg": 0.097365,
      "inclusive_time_rank_max": 0.128599,
      "inclusive_time_rank_min": 0.07352
    },
    {
      "path": "main/finitialize/cur-kdr",
      "Exclusive time %": 8e-06,
      "Inclusive time %": 8e-06,
      "exclusive_time_rank_avg": 1.8e-05,
      "exclusive_time_rank_max": 4e-05,
      "exclusive_time_rank_min": 1.6e-05,
      "inclusive_time_rank_avg": 1.8e-05,
      "inclusive_time_rank_max": 4e-05,
      "inclusive_time_rank_min": 1.6e-05
    },
    {
      "path": "main/simulation/timestep/deliver-events/net-receive-ProbAMPANMDA_EMS",
      "Exclusive time %": 0.006624,
      "Inclusive time %": 0.006624,
      "exclusive_time_rank_avg": 0.014539,
      "exclusive_time_rank_max": 0.015808,
      "exclusive_time_rank_min": 0.012984,
      "inclusive_time_rank_avg": 0.014539,
      "inclusive_time_rank_max": 0.015808,
      "inclusive_time_rank_min": 0.012984
    },
    {
      "path": "main/handle-forward-skip/timestep/state-update/state-kca",
      "Exclusive time %": 5.8e-05,
      "Inclusive time %": 5.8e-05,
      "exclusive_time_rank_avg": 0.000127,
      "exclusive_time_rank_max": 0.000172,
      "exclusive_time_rank_min": 0.000119,
      "inclusive_time_rank_avg": 0.000127,
      "inclusive_time_rank_max": 0.000172,
      "inclusive_time_rank_min": 0.000119
    },
    {
      "path": "main/simulation/timestep/matrix-solver",
      "Exclusive time %": 15.990273,
      "Inclusive time %": 15.990273,
      "exclusive_time_rank_avg": 35.09855,
      "exclusive_time_rank_max": 36.970455,
      "exclusive_time_rank_min": 33.167512,
      "inclusive_time_rank_avg": 35.09855,
      "inclusive_time_rank_max": 36.970455,
      "inclusive_time_rank_min": 33.167512
    },
    {
      "path": "main/handle-forward-skip/timestep/setup-tree-matrix/cur-kdr",
      "Exclusive time %": 6.8e-05,
      "Inclusive time %": 6.8e-05,
      "exclusive_time_rank_avg": 0.00015,
      "exclusive_time_rank_max": 0.00043,
      "exclusive_time_rank_min": 0.000119,
      "inclusive_time_rank_avg": 0.00015,
      "inclusive_time_rank_max": 0.00043,
      "inclusive_time_rank_min": 0.000119
    },
    {
      "path": "main/finitialize/cur-cacum",
      "Exclusive time %": 1e-05,
      "Inclusive time %": 1e-05,
      "exclusive_time_rank_avg": 2.2e-05,
      "exclusive_time_rank_max": 4.4e-05,
      "exclusive_time_rank_min": 1.7e-05,
      "inclusive_time_rank_avg": 2.2e-05,
      "inclusive_time_rank_max": 4.4e-05,
      "inclusive_time_rank_min": 1.7e-05
    },
    {
      "path": "main/simulation/timestep/setup-tree-matrix/cur-kdr",
      "Exclusive time %": 0.026147,
      "Inclusive time %": 0.026147,
      "exclusive_time_rank_avg": 0.057393,
      "exclusive_time_rank_max": 0.065831,
      "exclusive_time_rank_min": 0.053925,
      "inclusive_time_rank_avg": 0.057393,
      "inclusive_time_rank_max": 0.065831,
      "inclusive_time_rank_min": 0.053925
    },
    {
      "path": "main/simulation/timestep/state-update/state-kca",
      "Exclusive time %": 0.022943,
      "Inclusive time %": 0.022943,
      "exclusive_time_rank_avg": 0.05036,
      "exclusive_time_rank_max": 0.058341,
      "exclusive_time_rank_min": 0.048606,
      "inclusive_time_rank_avg": 0.05036,
      "inclusive_time_rank_max": 0.058341,
      "inclusive_time_rank_min": 0.048606
    },
    {
      "path": "main/output-spike/MPI_File_write_at_all",
      "Exclusive time %": 0.065977,
      "Inclusive time %": 0.065977,
      "exclusive_time_rank_avg": 0.144819,
      "exclusive_time_rank_max": 0.164687,
      "exclusive_time_rank_min": 0.004499,
      "inclusive_time_rank_avg": 0.144819,
      "inclusive_time_rank_max": 0.164687,
      "inclusive_time_rank_min": 0.004499
    },
    {
      "path": "main/simulation/timestep/setup-tree-matrix/cur-cacum",
      "Exclusive time %": 0.030213,
      "Inclusive time %": 0.030213,
      "exclusive_time_rank_avg": 0.066318,
      "exclusive_time_rank_max": 0.072677,
      "exclusive_time_rank_min": 0.062494,
      "inclusive_time_rank_avg": 0.066318,
      "inclusive_time_rank_max": 0.072677,
      "inclusive_time_rank_min": 0.062494
    },
    {
      "path": "main/handle-forward-skip/timestep/setup-tree-matrix/cur-cacum",
      "Exclusive time %": 7.7e-05,
      "Inclusive time %": 7.7e-05,
      "exclusive_time_rank_avg": 0.000169,
      "exclusive_time_rank_max": 0.00044,
      "exclusive_time_rank_min": 0.000133,
      "inclusive_time_rank_avg": 0.000169,
      "inclusive_time_rank_max": 0.00044,
      "inclusive_time_rank_min": 0.000133
    },
    {
      "path": "main/finitialize/cur-kmb",
      "Exclusive time %": 9e-06,
      "Inclusive time %": 9e-06,
      "exclusive_time_rank_avg": 2e-05,
      "exclusive_time_rank_max": 0.000101,
      "exclusive_time_rank_min": 1.6e-05,
      "inclusive_time_rank_avg": 2e-05,
      "inclusive_time_rank_max": 0.000101,
      "inclusive_time_rank_min": 1.6e-05
    },
    {
      "path": "main/handle-forward-skip/timestep/second-order-cur",
      "Exclusive time %": 7e-06,
      "Inclusive time %": 7e-06,
      "exclusive_time_rank_avg": 1.6e-05,
      "exclusive_time_rank_max": 2.3e-05,
      "exclusive_time_rank_min": 1.2e-05,
      "inclusive_time_rank_avg": 1.6e-05,
      "inclusive_time_rank_max": 2.3e-05,
      "inclusive_time_rank_min": 1.2e-05
    },
    {
      "path": "main/handle-forward-skip/timestep/state-update/state-kdb",
      "Exclusive time %": 5.5e-05,
      "Inclusive time %": 5.5e-05,
      "exclusive_time_rank_avg": 0.00012,
      "exclusive_time_rank_max": 0.000154,
      "exclusive_time_rank_min": 0.000112,
      "inclusive_time_rank_avg": 0.00012,
      "inclusive_time_rank_max": 0.000154,
      "inclusive_time_rank_min": 0.000112
    },
    {
      "path": "main/simulation/timestep/deliver-events/update-net-receive-buf/net-receive-buf-order",
      "Exclusive time %": 0.009671,
      "Inclusive time %": 0.009671,
      "exclusive_time_rank_avg": 0.021228,
      "exclusive_time_rank_max": 0.023651,
      "exclusive_time_rank_min": 0.019833,
      "inclusive_time_rank_avg": 0.021228,
      "inclusive_time_rank_max": 0.023651,
      "inclusive_time_rank_min": 0.019833
    },
    {
      "path": "main/handle-forward-skip/timestep/setup-tree-matrix/cur-kmb",
      "Exclusive time %": 6.6e-05,
      "Inclusive time %": 6.6e-05,
      "exclusive_time_rank_avg": 0.000144,
      "exclusive_time_rank_max": 0.000383,
      "exclusive_time_rank_min": 0.000119,
      "inclusive_time_rank_avg": 0.000144,
      "inclusive_time_rank_max": 0.000383,
      "inclusive_time_rank_min": 0.000119
    },
    {
      "path": "main/simulation/timestep/second-order-cur",
      "Exclusive time %": 0.003002,
      "Inclusive time %": 0.003002,
      "exclusive_time_rank_avg": 0.006588,
      "exclusive_time_rank_max": 0.008141,
      "exclusive_time_rank_min": 0.00623,
      "inclusive_time_rank_avg": 0.006588,
      "inclusive_time_rank_max": 0.008141,
      "inclusive_time_rank_min": 0.00623
    },
    {
      "path": "main/simulation/timestep/setup-tree-matrix/cur-kmb",
      "Exclusive time %": 0.026163,
      "Inclusive time %": 0.026163,
      "exclusive_time_rank_avg": 0.057429,
      "exclusive_time_rank_max": 0.065492,
      "exclusive_time_rank_min": 0.054653,
      "inclusive_time_rank_avg": 0.057429,
      "inclusive_time_rank_max": 0.065492,
      "inclusive_time_rank_min": 0.054653
    },
    {
      "path": "main/finitialize/cur-cagk",
      "Exclusive time %": 8e-06,
      "Inclusive time %": 8e-06,
      "exclusive_time_rank_avg": 1.8e-05,
      "exclusive_time_rank_max": 4e-05,
      "exclusive_time_rank_min": 1.5e-05,
      "inclusive_time_rank_avg": 1.8e-05,
      "inclusive_time_rank_max": 4e-05,
      "inclusive_time_rank_min": 1.5e-05
    },
    {
      "path": "main/simulation/timestep/state-update/state-kdb",
      "Exclusive time %": 0.021531,
      "Inclusive time %": 0.021531,
      "exclusive_time_rank_avg": 0.047261,
      "exclusive_time_rank_max": 0.054615,
      "exclusive_time_rank_min": 0.045223,
      "inclusive_time_rank_avg": 0.047261,
      "inclusive_time_rank_max": 0.054615,
      "inclusive_time_rank_min": 0.045223
    },
    {
      "path": "main/output-spike/MPI_File_close",
      "Exclusive time %": 0.010242,
      "Inclusive time %": 0.010242,
      "exclusive_time_rank_avg": 0.022482,
      "exclusive_time_rank_max": 0.161635,
      "exclusive_time_rank_min": 0.001508,
      "inclusive_time_rank_avg": 0.022482,
      "inclusive_time_rank_max": 0.161635,
      "inclusive_time_rank_min": 0.001508
    },
    {
      "path": "main/simulation/timestep/setup-tree-matrix/cur-cagk",
      "Exclusive time %": 0.028221,
      "Inclusive time %": 0.028221,
      "exclusive_time_rank_avg": 0.061944,
      "exclusive_time_rank_max": 0.069397,
      "exclusive_time_rank_min": 0.058423,
      "inclusive_time_rank_avg": 0.061944,
      "inclusive_time_rank_max": 0.069397,
      "inclusive_time_rank_min": 0.058423
    },
    {
      "path": "main/finitialize/cur-na3",
      "Exclusive time %": 9e-06,
      "Inclusive time %": 9e-06,
      "exclusive_time_rank_avg": 2e-05,
      "exclusive_time_rank_max": 4.2e-05,
      "exclusive_time_rank_min": 1.7e-05,
      "inclusive_time_rank_avg": 2e-05,
      "inclusive_time_rank_max": 4.2e-05,
      "inclusive_time_rank_min": 1.7e-05
    },
    {
      "path": "main/handle-forward-skip/timestep/setup-tree-matrix/cur-cagk",
      "Exclusive time %": 7.1e-05,
      "Inclusive time %": 7.1e-05,
      "exclusive_time_rank_avg": 0.000157,
      "exclusive_time_rank_max": 0.00031,
      "exclusive_time_rank_min": 0.000124,
      "inclusive_time_rank_avg": 0.000157,
      "inclusive_time_rank_max": 0.00031,
      "inclusive_time_rank_min": 0.000124
    },
    {
      "path": "main/handle-forward-skip/timestep/update",
      "Exclusive time %": 6.7e-05,
      "Inclusive time %": 6.7e-05,
      "exclusive_time_rank_avg": 0.000147,
      "exclusive_time_rank_max": 0.000179,
      "exclusive_time_rank_min": 0.000135,
      "inclusive_time_rank_avg": 0.000147,
      "inclusive_time_rank_max": 0.000179,
      "inclusive_time_rank_min": 0.000135
    },
    {
      "path": "main/handle-forward-skip/timestep/state-update/state-kdrb",
      "Exclusive time %": 5.4e-05,
      "Inclusive time %": 5.4e-05,
      "exclusive_time_rank_avg": 0.00012,
      "exclusive_time_rank_max": 0.000143,
      "exclusive_time_rank_min": 0.000111,
      "inclusive_time_rank_avg": 0.00012,
      "inclusive_time_rank_max": 0.000143,
      "inclusive_time_rank_min": 0.000111
    },
    {
      "path": "main/simulation/timestep/deliver-events/update-net-receive-buf/net-receive-buf-cpu2gpu",
      "Exclusive time %": 11.03907,
      "Inclusive time %": 11.03907,
      "exclusive_time_rank_avg": 24.23069,
      "exclusive_time_rank_max": 24.795445,
      "exclusive_time_rank_min": 23.449685,
      "inclusive_time_rank_avg": 24.23069,
      "inclusive_time_rank_max": 24.795445,
      "inclusive_time_rank_min": 23.449685
    },
    {
      "path": "main/handle-forward-skip/timestep/setup-tree-matrix/cur-na3",
      "Exclusive time %": 6.8e-05,
      "Inclusive time %": 6.8e-05,
      "exclusive_time_rank_avg": 0.00015,
      "exclusive_time_rank_max": 0.000256,
      "exclusive_time_rank_min": 0.000126,
      "inclusive_time_rank_avg": 0.00015,
      "inclusive_time_rank_max": 0.000256,
      "inclusive_time_rank_min": 0.000126
    },
    {
      "path": "main/simulation/timestep/setup-tree-matrix/cur-na3",
      "Exclusive time %": 0.027621,
      "Inclusive time %": 0.027621,
      "exclusive_time_rank_avg": 0.060627,
      "exclusive_time_rank_max": 0.067437,
      "exclusive_time_rank_min": 0.058257,
      "inclusive_time_rank_avg": 0.060627,
      "inclusive_time_rank_max": 0.067437,
      "inclusive_time_rank_min": 0.058257
    },
    {
      "path": "main/simulation/timestep/update",
      "Exclusive time %": 0.025464,
      "Inclusive time %": 0.025464,
      "exclusive_time_rank_avg": 0.055893,
      "exclusive_time_rank_max": 0.069602,
      "exclusive_time_rank_min": 0.053106,
      "inclusive_time_rank_avg": 0.055893,
      "inclusive_time_rank_max": 0.069602,
      "inclusive_time_rank_min": 0.053106
    },
    {
      "path": "main/simulation/timestep/state-update/state-kdrb",
      "Exclusive time %": 0.021374,
      "Inclusive time %": 0.021374,
      "exclusive_time_rank_avg": 0.046917,
      "exclusive_time_rank_max": 0.054538,
      "exclusive_time_rank_min": 0.045458,
      "inclusive_time_rank_avg": 0.046917,
      "inclusive_time_rank_max": 0.054538,
      "inclusive_time_rank_min": 0.045458
    },
    {
      "path": "main/finitialize/cur-cal",
      "Exclusive time %": 9e-06,
      "Inclusive time %": 9e-06,
      "exclusive_time_rank_avg": 1.9e-05,
      "exclusive_time_rank_max": 5e-05,
      "exclusive_time_rank_min": 1.5e-05,
      "inclusive_time_rank_avg": 1.9e-05,
      "inclusive_time_rank_max": 5e-05,
      "inclusive_time_rank_min": 1.5e-05
    },
    {
      "path": "main/checkpoint",
      "Exclusive time %": 2e-06,
      "Inclusive time %": 2e-06,
      "exclusive_time_rank_avg": 4e-06,
      "exclusive_time_rank_max": 5e-06,
      "exclusive_time_rank_min": 3e-06,
      "inclusive_time_rank_avg": 4e-06,
      "inclusive_time_rank_max": 5e-06,
      "inclusive_time_rank_min": 3e-06
    },
    {
      "path": "main/finitialize/cur-nax",
      "Exclusive time %": 8e-06,
      "Inclusive time %": 8e-06,
      "exclusive_time_rank_avg": 1.8e-05,
      "exclusive_time_rank_max": 3.2e-05,
      "exclusive_time_rank_min": 1.5e-05,
      "inclusive_time_rank_avg": 1.8e-05,
      "inclusive_time_rank_max": 3.2e-05,
      "inclusive_time_rank_min": 1.5e-05
    },
    {
      "path": "main/simulation/timestep/setup-tree-matrix/cur-cal",
      "Exclusive time %": 0.027972,
      "Inclusive time %": 0.027972,
      "exclusive_time_rank_avg": 0.061398,
      "exclusive_time_rank_max": 0.067912,
      "exclusive_time_rank_min": 0.057292,
      "inclusive_time_rank_avg": 0.061398,
      "inclusive_time_rank_max": 0.067912,
      "inclusive_time_rank_min": 0.057292
    },
    {
      "path": "main/handle-forward-skip/timestep/setup-tree-matrix/cur-cal",
      "Exclusive time %": 7.7e-05,
      "Inclusive time %": 7.7e-05,
      "exclusive_time_rank_avg": 0.00017,
      "exclusive_time_rank_max": 0.000536,
      "exclusive_time_rank_min": 0.000122,
      "inclusive_time_rank_avg": 0.00017,
      "inclusive_time_rank_max": 0.000536,
      "inclusive_time_rank_min": 0.000122
    },
    {
      "path": "main/handle-forward-skip/timestep/state-update/state-kdr",
      "Exclusive time %": 5.3e-05,
      "Inclusive time %": 5.3e-05,
      "exclusive_time_rank_avg": 0.000117,
      "exclusive_time_rank_max": 0.000135,
      "exclusive_time_rank_min": 0.000109,
      "inclusive_time_rank_avg": 0.000117,
      "inclusive_time_rank_max": 0.000135,
      "inclusive_time_rank_min": 0.000109
    },
    {
      "path": "main/handle-forward-skip/timestep/state-update",
      "Exclusive time %": 0.000123,
      "Inclusive time %": 0.001059,
      "exclusive_time_rank_avg": 0.00027,
      "exclusive_time_rank_max": 0.000314,
      "exclusive_time_rank_min": 0.000251,
      "inclusive_time_rank_avg": 0.002325,
      "inclusive_time_rank_max": 0.002656,
      "inclusive_time_rank_min": 0.002225
    },
    {
      "path": "main/handle-forward-skip/timestep/setup-tree-matrix/cur-nax",
      "Exclusive time %": 6.3e-05,
      "Inclusive time %": 6.3e-05,
      "exclusive_time_rank_avg": 0.000139,
      "exclusive_time_rank_max": 0.000276,
      "exclusive_time_rank_min": 0.000118,
      "inclusive_time_rank_avg": 0.000139,
      "inclusive_time_rank_max": 0.000276,
      "inclusive_time_rank_min": 0.000118
    },
    {
      "path": "main/simulation/timestep/setup-tree-matrix/cur-nax",
      "Exclusive time %": 0.025866,
      "Inclusive time %": 0.025866,
      "exclusive_time_rank_avg": 0.056775,
      "exclusive_time_rank_max": 0.064861,
      "exclusive_time_rank_min": 0.054109,
      "inclusive_time_rank_avg": 0.056775,
      "inclusive_time_rank_max": 0.064861,
      "inclusive_time_rank_min": 0.054109
    },
    {
      "path": "main/simulation/timestep/state-update/state-kdr",
      "Exclusive time %": 0.021128,
      "Inclusive time %": 0.021128,
      "exclusive_time_rank_avg": 0.046376,
      "exclusive_time_rank_max": 0.054273,
      "exclusive_time_rank_min": 0.044856,
      "inclusive_time_rank_avg": 0.046376,
      "inclusive_time_rank_max": 0.054273,
      "inclusive_time_rank_min": 0.044856
    },
    {
      "path": "main/finitialize/cur-ProbAMPANMDA_EMS",
      "Exclusive time %": 8e-06,
      "Inclusive time %": 8e-06,
      "exclusive_time_rank_avg": 1.8e-05,
      "exclusive_time_rank_max": 6.3e-05,
      "exclusive_time_rank_min": 1.5e-05,
      "inclusive_time_rank_avg": 1.8e-05,
      "inclusive_time_rank_max": 6.3e-05,
      "inclusive_time_rank_min": 1.5e-05
    },
    {
      "path": "main/handle-forward-skip/timestep/state-update/state-kmb",
      "Exclusive time %": 5.3e-05,
      "Inclusive time %": 5.3e-05,
      "exclusive_time_rank_avg": 0.000117,
      "exclusive_time_rank_max": 0.000139,
      "exclusive_time_rank_min": 0.000109,
      "inclusive_time_rank_avg": 0.000117,
      "inclusive_time_rank_max": 0.000139,
      "inclusive_time_rank_min": 0.000109
    },
    {
      "path": "main/MPI_Comm_free",
      "Exclusive time %": 0.003605,
      "Inclusive time %": 0.003605,
      "exclusive_time_rank_avg": 0.007914,
      "exclusive_time_rank_max": 0.023515,
      "exclusive_time_rank_min": 0.001126,
      "inclusive_time_rank_avg": 0.007914,
      "inclusive_time_rank_max": 0.023515,
      "inclusive_time_rank_min": 0.001126
    },
    {
      "path": "main/handle-forward-skip/timestep/setup-tree-matrix/cur-ProbAMPANMDA_EMS",
      "Exclusive time %": 6.5e-05,
      "Inclusive time %": 6.5e-05,
      "exclusive_time_rank_avg": 0.000142,
      "exclusive_time_rank_max": 0.000296,
      "exclusive_time_rank_min": 0.00012,
      "inclusive_time_rank_avg": 0.000142,
      "inclusive_time_rank_max": 0.000296,
      "inclusive_time_rank_min": 0.00012
    },
    {
      "path": "main/simulation/timestep/setup-tree-matrix/cur-ProbAMPANMDA_EMS",
      "Exclusive time %": 0.026112,
      "Inclusive time %": 0.026112,
      "exclusive_time_rank_avg": 0.057315,
      "exclusive_time_rank_max": 0.064996,
      "exclusive_time_rank_min": 0.054223,
      "inclusive_time_rank_avg": 0.057315,
      "inclusive_time_rank_max": 0.064996,
      "inclusive_time_rank_min": 0.054223
    },
    {
      "path": "main/simulation/timestep/state-update/state-kmb",
      "Exclusive time %": 0.021084,
      "Inclusive time %": 0.021084,
      "exclusive_time_rank_avg": 0.04628,
      "exclusive_time_rank_max": 0.054359,
      "exclusive_time_rank_min": 0.044205,
      "inclusive_time_rank_avg": 0.04628,
      "inclusive_time_rank_max": 0.054359,
      "inclusive_time_rank_min": 0.044205
    },
    {
      "path": "main/finitialize/cur-ProbGABAAB_EMS",
      "Exclusive time %": 8e-06,
      "Inclusive time %": 8e-06,
      "exclusive_time_rank_avg": 1.8e-05,
      "exclusive_time_rank_max": 6.8e-05,
      "exclusive_time_rank_min": 1.5e-05,
      "inclusive_time_rank_avg": 1.8e-05,
      "inclusive_time_rank_max": 6.8e-05,
      "inclusive_time_rank_min": 1.5e-05
    },
    {
      "path": "main/handle-forward-skip/timestep/state-update/state-na3",
      "Exclusive time %": 5.8e-05,
      "Inclusive time %": 5.8e-05,
      "exclusive_time_rank_avg": 0.000127,
      "exclusive_time_rank_max": 0.00015,
      "exclusive_time_rank_min": 0.000119,
      "inclusive_time_rank_avg": 0.000127,
      "inclusive_time_rank_max": 0.00015,
      "inclusive_time_rank_min": 0.000119
    },
    {
      "path": "main/MPI_Finalize",
      "Exclusive time %": 0.014276,
      "Inclusive time %": 0.014276,
      "exclusive_time_rank_avg": 0.031336,
      "exclusive_time_rank_max": 0.032102,
      "exclusive_time_rank_min": 0.030582,
      "inclusive_time_rank_avg": 0.031336,
      "inclusive_time_rank_max": 0.032102,
      "inclusive_time_rank_min": 0.030582
    },
    {
      "path": "main/simulation/timestep/deliver-events/net-receive-ProbGABAAB_EMS",
      "Exclusive time %": 0.038084,
      "Inclusive time %": 0.038084,
      "exclusive_time_rank_avg": 0.083595,
      "exclusive_time_rank_max": 0.088656,
      "exclusive_time_rank_min": 0.078393,
      "inclusive_time_rank_avg": 0.083595,
      "inclusive_time_rank_max": 0.088656,
      "inclusive_time_rank_min": 0.078393
    },
    {
      "path": "main/handle-forward-skip/timestep/setup-tree-matrix/cur-ProbGABAAB_EMS",
      "Exclusive time %": 6.7e-05,
      "Inclusive time %": 6.7e-05,
      "exclusive_time_rank_avg": 0.000148,
      "exclusive_time_rank_max": 0.000554,
      "exclusive_time_rank_min": 0.00012,
      "inclusive_time_rank_avg": 0.000148,
      "inclusive_time_rank_max": 0.000554,
      "inclusive_time_rank_min": 0.00012
    },
    {
      "path": "main/simulation/timestep/setup-tree-matrix/cur-ProbGABAAB_EMS",
      "Exclusive time %": 0.025805,
      "Inclusive time %": 0.025805,
      "exclusive_time_rank_avg": 0.056641,
      "exclusive_time_rank_max": 0.064038,
      "exclusive_time_rank_min": 0.053749,
      "inclusive_time_rank_avg": 0.056641,
      "inclusive_time_rank_max": 0.064038,
      "inclusive_time_rank_min": 0.053749
    },
    {
      "path": "main/simulation/timestep/state-update",
      "Exclusive time %": 0.048437,
      "Inclusive time %": 0.418362,
      "exclusive_time_rank_avg": 0.106318,
      "exclusive_time_rank_max": 0.124672,
      "exclusive_time_rank_min": 0.103552,
      "inclusive_time_rank_avg": 0.918302,
      "inclusive_time_rank_max": 1.065368,
      "inclusive_time_rank_min": 0.893704
    },
    {
      "path": "main/simulation/timestep/state-update/state-na3",
      "Exclusive time %": 0.023058,
      "Inclusive time %": 0.023058,
      "exclusive_time_rank_avg": 0.050612,
      "exclusive_time_rank_max": 0.057943,
      "exclusive_time_rank_min": 0.04827,
      "inclusive_time_rank_avg": 0.050612,
      "inclusive_time_rank_max": 0.057943,
      "inclusive_time_rank_min": 0.04827
    },
    {
      "path": "main/finitialize/cur-can",
      "Exclusive time %": 9e-06,
      "Inclusive time %": 9e-06,
      "exclusive_time_rank_avg": 1.9e-05,
      "exclusive_time_rank_max": 6.5e-05,
      "exclusive_time_rank_min": 1.5e-05,
      "inclusive_time_rank_avg": 1.9e-05,
      "inclusive_time_rank_max": 6.5e-05,
      "inclusive_time_rank_min": 1.5e-05
    },
    {
      "path": "main/handle-forward-skip/timestep/state-update/state-cacum",
      "Exclusive time %": 6.6e-05,
      "Inclusive time %": 6.6e-05,
      "exclusive_time_rank_avg": 0.000146,
      "exclusive_time_rank_max": 0.000171,
      "exclusive_time_rank_min": 0.000136,
      "inclusive_time_rank_avg": 0.000146,
      "inclusive_time_rank_max": 0.000171,
      "inclusive_time_rank_min": 0.000136
    },
    {
      "path": "main/handle-forward-skip/timestep/state-update/state-nax",
      "Exclusive time %": 5.4e-05,
      "Inclusive time %": 5.4e-05,
      "exclusive_time_rank_avg": 0.000118,
      "exclusive_time_rank_max": 0.000134,
      "exclusive_time_rank_min": 0.000111,
      "inclusive_time_rank_avg": 0.000118,
      "inclusive_time_rank_max": 0.000134,
      "inclusive_time_rank_min": 0.000111
    },
    {
      "path": "main/handle-forward-skip/timestep/setup-tree-matrix/cur-can",
      "Exclusive time %": 6.7e-05,
      "Inclusive time %": 6.7e-05,
      "exclusive_time_rank_avg": 0.000146,
      "exclusive_time_rank_max": 0.000415,
      "exclusive_time_rank_min": 0.000122,
      "inclusive_time_rank_avg": 0.000146,
      "inclusive_time_rank_max": 0.000415,
      "inclusive_time_rank_min": 0.000122
    },
    {
      "path": "main/simulation/timestep/setup-tree-matrix/cur-can",
      "Exclusive time %": 0.027304,
      "Inclusive time %": 0.027304,
      "exclusive_time_rank_avg": 0.059932,
      "exclusive_time_rank_max": 0.065463,
      "exclusive_time_rank_min": 0.056805,
      "inclusive_time_rank_avg": 0.059932,
      "inclusive_time_rank_max": 0.065463,
      "inclusive_time_rank_min": 0.056805
    },
    {
      "path": "main/MPI_Comm_dup",
      "Exclusive time %": 0.000583,
      "Inclusive time %": 0.000583,
      "exclusive_time_rank_avg": 0.001281,
      "exclusive_time_rank_max": 0.001426,
      "exclusive_time_rank_min": 0.001194,
      "inclusive_time_rank_avg": 0.001281,
      "inclusive_time_rank_max": 0.001426,
      "inclusive_time_rank_min": 0.001194
    },
    {
      "path": "main/simulation/timestep/state-update/state-cacum",
      "Exclusive time %": 0.026797,
      "Inclusive time %": 0.026797,
      "exclusive_time_rank_avg": 0.05882,
      "exclusive_time_rank_max": 0.066545,
      "exclusive_time_rank_min": 0.056786,
      "inclusive_time_rank_avg": 0.05882,
      "inclusive_time_rank_max": 0.066545,
      "inclusive_time_rank_min": 0.056786
    },
    {
      "path": "main/simulation/spike-exchange/communication/MPI_Allgatherv",
      "Exclusive time %": 0.023012,
      "Inclusive time %": 0.023012,
      "exclusive_time_rank_avg": 0.050512,
      "exclusive_time_rank_max": 0.053772,
      "exclusive_time_rank_min": 0.047603,
      "inclusive_time_rank_avg": 0.050512,
      "inclusive_time_rank_max": 0.053772,
      "inclusive_time_rank_min": 0.047603
    },
    {
      "path": "main/simulation/timestep/state-update/state-nax",
      "Exclusive time %": 0.021035,
      "Inclusive time %": 0.021035,
      "exclusive_time_rank_avg": 0.046173,
      "exclusive_time_rank_max": 0.053565,
      "exclusive_time_rank_min": 0.044535,
      "inclusive_time_rank_avg": 0.046173,
      "inclusive_time_rank_max": 0.053565,
      "inclusive_time_rank_min": 0.044535
    },
    {
      "path": "main/finitialize/cur-cat",
      "Exclusive time %": 8e-06,
      "Inclusive time %": 8e-06,
      "exclusive_time_rank_avg": 1.8e-05,
      "exclusive_time_rank_max": 7.7e-05,
      "exclusive_time_rank_min": 1.5e-05,
      "inclusive_time_rank_avg": 1.8e-05,
      "inclusive_time_rank_max": 7.7e-05,
      "inclusive_time_rank_min": 1.5e-05
    },
    {
      "path": "main/handle-forward-skip/timestep/state-update/state-ProbAMPANMDA_EMS",
      "Exclusive time %": 5.2e-05,
      "Inclusive time %": 5.2e-05,
      "exclusive_time_rank_avg": 0.000114,
      "exclusive_time_rank_max": 0.000144,
      "exclusive_time_rank_min": 0.000105,
      "inclusive_time_rank_avg": 0.000114,
      "inclusive_time_rank_max": 0.000144,
      "inclusive_time_rank_min": 0.000105
    },
    {
      "path": "main/handle-forward-skip/timestep/state-update/state-cagk",
      "Exclusive time %": 5.6e-05,
      "Inclusive time %": 5.6e-05,
      "exclusive_time_rank_avg": 0.000123,
      "exclusive_time_rank_max": 0.00015,
      "exclusive_time_rank_min": 0.000115,
      "inclusive_time_rank_avg": 0.000123,
      "inclusive_time_rank_max": 0.00015,
      "inclusive_time_rank_min": 0.000115
    },
    {
      "path": "main/simulation/timestep/state-update/state-ProbAMPANMDA_EMS",
      "Exclusive time %": 0.020348,
      "Inclusive time %": 0.020348,
      "exclusive_time_rank_avg": 0.044665,
      "exclusive_time_rank_max": 0.053011,
      "exclusive_time_rank_min": 0.043035,
      "inclusive_time_rank_avg": 0.044665,
      "inclusive_time_rank_max": 0.053011,
      "inclusive_time_rank_min": 0.043035
    },
    {
      "path": "main/finitialize/spike-exchange/communication",
      "Exclusive time %": 9.3e-05,
      "Inclusive time %": 0.000182,
      "exclusive_time_rank_avg": 0.000204,
      "exclusive_time_rank_max": 0.000308,
      "exclusive_time_rank_min": 1.4e-05,
      "inclusive_time_rank_avg": 0.0004,
      "inclusive_time_rank_max": 0.00044,
      "inclusive_time_rank_min": 0.00036
    },
    {
      "path": "main/handle-forward-skip/timestep/setup-tree-matrix/cur-cat",
      "Exclusive time %": 7.1e-05,
      "Inclusive time %": 7.1e-05,
      "exclusive_time_rank_avg": 0.000155,
      "exclusive_time_rank_max": 0.000395,
      "exclusive_time_rank_min": 0.00012,
      "inclusive_time_rank_avg": 0.000155,
      "inclusive_time_rank_max": 0.000395,
      "inclusive_time_rank_min": 0.00012
    },
    {
      "path": "main/simulation/timestep/setup-tree-matrix/cur-cat",
      "Exclusive time %": 0.027071,
      "Inclusive time %": 0.027071,
      "exclusive_time_rank_avg": 0.05942,
      "exclusive_time_rank_max": 0.06661,
      "exclusive_time_rank_min": 0.055321,
      "inclusive_time_rank_avg": 0.05942,
      "inclusive_time_rank_max": 0.06661,
      "inclusive_time_rank_min": 0.055321
    },
    {
      "path": "main/simulation/timestep/state-update/state-cagk",
      "Exclusive time %": 0.022282,
      "Inclusive time %": 0.022282,
      "exclusive_time_rank_avg": 0.048908,
      "exclusive_time_rank_max": 0.056082,
      "exclusive_time_rank_min": 0.047582,
      "inclusive_time_rank_avg": 0.048908,
      "inclusive_time_rank_max": 0.056082,
      "inclusive_time_rank_min": 0.047582
    },
    {
      "path": "main/handle-forward-skip/timestep/state-update/state-ProbGABAAB_EMS",
      "Exclusive time %": 5.1e-05,
      "Inclusive time %": 5.1e-05,
      "exclusive_time_rank_avg": 0.000113,
      "exclusive_time_rank_max": 0.000129,
      "exclusive_time_rank_min": 0.000104,
      "inclusive_time_rank_avg": 0.000113,
      "inclusive_time_rank_max": 0.000129,
      "inclusive_time_rank_min": 0.000104
    },
    {
      "path": "main/finitialize/cur-hd",
      "Exclusive time %": 8e-06,
      "Inclusive time %": 8e-06,
      "exclusive_time_rank_avg": 1.7e-05,
      "exclusive_time_rank_max": 4e-05,
      "exclusive_time_rank_min": 1.4e-05,
      "inclusive_time_rank_avg": 1.7e-05,
      "inclusive_time_rank_max": 4e-05,
      "inclusive_time_rank_min": 1.4e-05
    },
    {
      "path": "main/simulation/timestep/state-update/state-ProbGABAAB_EMS",
      "Exclusive time %": 0.019917,
      "Inclusive time %": 0.019917,
      "exclusive_time_rank_avg": 0.043717,
      "exclusive_time_rank_max": 0.052178,
      "exclusive_time_rank_min": 0.042057,
      "inclusive_time_rank_avg": 0.043717,
      "inclusive_time_rank_max": 0.052178,
      "inclusive_time_rank_min": 0.042057
    },
    {
      "path": "main/handle-forward-skip/timestep/state-update/state-cal",
      "Exclusive time %": 5.6e-05,
      "Inclusive time %": 5.6e-05,
      "exclusive_time_rank_avg": 0.000122,
      "exclusive_time_rank_max": 0.000154,
      "exclusive_time_rank_min": 0.000113,
      "inclusive_time_rank_avg": 0.000122,
      "inclusive_time_rank_max": 0.000154,
      "inclusive_time_rank_min": 0.000113
    },
    {
      "path": "main/finitialize/spike-exchange/communication/MPI_Allgather",
      "Exclusive time %": 8.9e-05,
      "Inclusive time %": 8.9e-05,
      "exclusive_time_rank_avg": 0.000196,
      "exclusive_time_rank_max": 0.000401,
      "exclusive_time_rank_min": 7.2e-05,
      "inclusive_time_rank_avg": 0.000196,
      "inclusive_time_rank_max": 0.000401,
      "inclusive_time_rank_min": 7.2e-05
    },
    {
      "path": "main/simulation/spike-exchange/communication/MPI_Allgather",
      "Exclusive time %": 0.016261,
      "Inclusive time %": 0.016261,
      "exclusive_time_rank_avg": 0.035693,
      "exclusive_time_rank_max": 0.04215,
      "exclusive_time_rank_min": 0.029155,
      "inclusive_time_rank_avg": 0.035693,
      "inclusive_time_rank_max": 0.04215,
      "inclusive_time_rank_min": 0.029155
    },
    {
      "path": "main/handle-forward-skip/timestep/setup-tree-matrix/cur-hd",
      "Exclusive time %": 6.5e-05,
      "Inclusive time %": 6.5e-05,
      "exclusive_time_rank_avg": 0.000142,
      "exclusive_time_rank_max": 0.000338,
      "exclusive_time_rank_min": 0.000114,
      "inclusive_time_rank_avg": 0.000142,
      "inclusive_time_rank_max": 0.000338,
      "inclusive_time_rank_min": 0.000114
    },
    {
      "path": "main/simulation/timestep/setup-tree-matrix/cur-hd",
      "Exclusive time %": 0.025842,
      "Inclusive time %": 0.025842,
      "exclusive_time_rank_avg": 0.056723,
      "exclusive_time_rank_max": 0.063591,
      "exclusive_time_rank_min": 0.053855,
      "inclusive_time_rank_avg": 0.056723,
      "inclusive_time_rank_max": 0.063591,
      "inclusive_time_rank_min": 0.053855
    },
    {
      "path": "main/simulation/timestep/state-update/state-cal",
      "Exclusive time %": 0.022278,
      "Inclusive time %": 0.022278,
      "exclusive_time_rank_avg": 0.0489,
      "exclusive_time_rank_max": 0.055942,
      "exclusive_time_rank_min": 0.047164,
      "inclusive_time_rank_avg": 0.0489,
      "inclusive_time_rank_max": 0.055942,
      "inclusive_time_rank_min": 0.047164
    },
    {
      "path": "main/output-spike/MPI_Initialized",
      "Exclusive time %": 2e-06,
      "Inclusive time %": 2e-06,
      "exclusive_time_rank_avg": 3e-06,
      "exclusive_time_rank_max": 5e-06,
      "exclusive_time_rank_min": 2e-06,
      "inclusive_time_rank_avg": 3e-06,
      "inclusive_time_rank_max": 5e-06,
      "inclusive_time_rank_min": 2e-06
    },
    {
      "path": "main/finitialize/cur-kad",
      "Exclusive time %": 8e-06,
      "Inclusive time %": 8e-06,
      "exclusive_time_rank_avg": 1.7e-05,
      "exclusive_time_rank_max": 3.3e-05,
      "exclusive_time_rank_min": 1.5e-05,
      "inclusive_time_rank_avg": 1.7e-05,
      "inclusive_time_rank_max": 3.3e-05,
      "inclusive_time_rank_min": 1.5e-05
    },
    {
      "path": "main/handle-forward-skip/timestep/state-update/state-can",
      "Exclusive time %": 5.4e-05,
      "Inclusive time %": 5.4e-05,
      "exclusive_time_rank_avg": 0.000119,
      "exclusive_time_rank_max": 0.00014,
      "exclusive_time_rank_min": 0.000111,
      "inclusive_time_rank_avg": 0.000119,
      "inclusive_time_rank_max": 0.00014,
      "inclusive_time_rank_min": 0.000111
    },
    {
      "path": "main/MPI_Initialized",
      "Exclusive time %": 7e-06,
      "Inclusive time %": 7e-06,
      "exclusive_time_rank_avg": 1.6e-05,
      "exclusive_time_rank_max": 4.1e-05,
      "exclusive_time_rank_min": 9e-06,
      "inclusive_time_rank_avg": 1.6e-05,
      "inclusive_time_rank_max": 4.1e-05,
      "inclusive_time_rank_min": 9e-06
    },
    {
      "path": "main/handle-forward-skip/timestep/setup-tree-matrix/cur-kad",
      "Exclusive time %": 6.6e-05,
      "Inclusive time %": 6.6e-05,
      "exclusive_time_rank_avg": 0.000146,
      "exclusive_time_rank_max": 0.000397,
      "exclusive_time_rank_min": 0.000121,
      "inclusive_time_rank_avg": 0.000146,
      "inclusive_time_rank_max": 0.000397,
      "inclusive_time_rank_min": 0.000121
    },
    {
      "path": "main/simulation/timestep/setup-tree-matrix/cur-kad",
      "Exclusive time %": 0.027119,
      "Inclusive time %": 0.027119,
      "exclusive_time_rank_avg": 0.059526,
      "exclusive_time_rank_max": 0.066978,
      "exclusive_time_rank_min": 0.055842,
      "inclusive_time_rank_avg": 0.059526,
      "inclusive_time_rank_max": 0.066978,
      "inclusive_time_rank_min": 0.055842
    },
    {
      "path": "main/simulation/timestep/state-update/state-can",
      "Exclusive time %": 0.021572,
      "Inclusive time %": 0.021572,
      "exclusive_time_rank_avg": 0.04735,
      "exclusive_time_rank_max": 0.054232,
      "exclusive_time_rank_min": 0.045917,
      "inclusive_time_rank_avg": 0.04735,
      "inclusive_time_rank_max": 0.054232,
      "inclusive_time_rank_min": 0.045917
    },
    {
      "path": "main/finitialize/cur-kap",
      "Exclusive time %": 8e-06,
      "Inclusive time %": 8e-06,
      "exclusive_time_rank_avg": 1.7e-05,
      "exclusive_time_rank_max": 4.3e-05,
      "exclusive_time_rank_min": 1.5e-05,
      "inclusive_time_rank_avg": 1.7e-05,
      "inclusive_time_rank_max": 4.3e-05,
      "inclusive_time_rank_min": 1.5e-05
    },
    {
      "path": "main/handle-forward-skip/timestep/deliver-events/check-threshold",
      "Exclusive time %": 0.001687,
      "Inclusive time %": 0.001687,
      "exclusive_time_rank_avg": 0.003702,
      "exclusive_time_rank_max": 0.007859,
      "exclusive_time_rank_min": 0.001798,
      "inclusive_time_rank_avg": 0.003702,
      "inclusive_time_rank_max": 0.007859,
      "inclusive_time_rank_min": 0.001798
    },
    {
      "path": "main/handle-forward-skip/timestep/state-update/state-cat",
      "Exclusive time %": 5.5e-05,
      "Inclusive time %": 5.5e-05,
      "exclusive_time_rank_avg": 0.000121,
      "exclusive_time_rank_max": 0.000153,
      "exclusive_time_rank_min": 0.000112,
      "inclusive_time_rank_avg": 0.000121,
      "inclusive_time_rank_max": 0.000153,
      "inclusive_time_rank_min": 0.000112
    },
    {
      "path": "main/simulation/timestep/deliver-events/check-threshold",
      "Exclusive time %": 0.533505,
      "Inclusive time %": 0.533505,
      "exclusive_time_rank_avg": 1.17104,
      "exclusive_time_rank_max": 1.236308,
      "exclusive_time_rank_min": 1.111394,
      "inclusive_time_rank_avg": 1.17104,
      "inclusive_time_rank_max": 1.236308,
      "inclusive_time_rank_min": 1.111394
    },
    {
      "path": "main/output-spike/MPI_Alltoall",
      "Exclusive time %": 0.000595,
      "Inclusive time %": 0.000595,
      "exclusive_time_rank_avg": 0.001306,
      "exclusive_time_rank_max": 0.001452,
      "exclusive_time_rank_min": 0.001215,
      "inclusive_time_rank_avg": 0.001306,
      "inclusive_time_rank_max": 0.001452,
      "inclusive_time_rank_min": 0.001215
    },
    {
      "path": "main/handle-forward-skip/timestep/deliver-events/net-buf-receive-ALU",
      "Exclusive time %": 1.2e-05,
      "Inclusive time %": 1.2e-05,
      "exclusive_time_rank_avg": 2.7e-05,
      "exclusive_time_rank_max": 4.2e-05,
      "exclusive_time_rank_min": 2.3e-05,
      "inclusive_time_rank_avg": 2.7e-05,
      "inclusive_time_rank_max": 4.2e-05,
      "inclusive_time_rank_min": 2.3e-05
    },
    {
      "path": "main/handle-forward-skip/timestep/setup-tree-matrix/cur-kap",
      "Exclusive time %": 6.6e-05,
      "Inclusive time %": 6.6e-05,
      "exclusive_time_rank_avg": 0.000145,
      "exclusive_time_rank_max": 0.000346,
      "exclusive_time_rank_min": 0.000122,
      "inclusive_time_rank_avg": 0.000145,
      "inclusive_time_rank_max": 0.000346,
      "inclusive_time_rank_min": 0.000122
    },
    {
      "path": "main/simulation/timestep/deliver-events/net-buf-receive-ALU",
      "Exclusive time %": 0.005306,
      "Inclusive time %": 0.005306,
      "exclusive_time_rank_avg": 0.011647,
      "exclusive_time_rank_max": 0.012864,
      "exclusive_time_rank_min": 0.011238,
      "inclusive_time_rank_avg": 0.011647,
      "inclusive_time_rank_max": 0.012864,
      "inclusive_time_rank_min": 0.011238
    },
    {
      "path": "main/simulation/timestep/setup-tree-matrix/cur-kap",
      "Exclusive time %": 0.02688,
      "Inclusive time %": 0.02688,
      "exclusive_time_rank_avg": 0.059002,
      "exclusive_time_rank_max": 0.066392,
      "exclusive_time_rank_min": 0.055808,
      "inclusive_time_rank_avg": 0.059002,
      "inclusive_time_rank_max": 0.066392,
      "inclusive_time_rank_min": 0.055808
    },
    {
      "path": "main/handle-forward-skip/timestep/deliver-events/net-buf-receive-DetAMPANMDA",
      "Exclusive time %": 1.2e-05,
      "Inclusive time %": 1.2e-05,
      "exclusive_time_rank_avg": 2.6e-05,
      "exclusive_time_rank_max": 3.7e-05,
      "exclusive_time_rank_min": 2.1e-05,
      "inclusive_time_rank_avg": 2.6e-05,
      "inclusive_time_rank_max": 3.7e-05,
      "inclusive_time_rank_min": 2.1e-05
    },
    {
      "path": "main/simulation/timestep/state-update/state-cat",
      "Exclusive time %": 0.021396,
      "Inclusive time %": 0.021396,
      "exclusive_time_rank_avg": 0.046963,
      "exclusive_time_rank_max": 0.054387,
      "exclusive_time_rank_min": 0.045267,
      "inclusive_time_rank_avg": 0.046963,
      "inclusive_time_rank_max": 0.054387,
      "inclusive_time_rank_min": 0.045267
    },
    {
      "path": "main/finitialize/cur-kca",
      "Exclusive time %": 9e-06,
      "Inclusive time %": 9e-06,
      "exclusive_time_rank_avg": 1.9e-05,
      "exclusive_time_rank_max": 2.7e-05,
      "exclusive_time_rank_min": 1.7e-05,
      "inclusive_time_rank_avg": 1.9e-05,
      "inclusive_time_rank_max": 2.7e-05,
      "inclusive_time_rank_min": 1.7e-05
    },
    {
      "path": "main/simulation/timestep/deliver-events/net-buf-receive-DetAMPANMDA",
      "Exclusive time %": 0.004875,
      "Inclusive time %": 0.004875,
      "exclusive_time_rank_avg": 0.010701,
      "exclusive_time_rank_max": 0.011453,
      "exclusive_time_rank_min": 0.010377,
      "inclusive_time_rank_avg": 0.010701,
      "inclusive_time_rank_max": 0.011453,
      "inclusive_time_rank_min": 0.010377
    },
    {
      "path": "main/handle-forward-skip/timestep/deliver-events/net-buf-receive-DetGABAAB",
      "Exclusive time %": 1.2e-05,
      "Inclusive time %": 1.2e-05,
      "exclusive_time_rank_avg": 2.6e-05,
      "exclusive_time_rank_max": 4e-05,
      "exclusive_time_rank_min": 2.1e-05,
      "inclusive_time_rank_avg": 2.6e-05,
      "inclusive_time_rank_max": 4e-05,
      "inclusive_time_rank_min": 2.1e-05
    },
    {
      "path": "main/handle-forward-skip/timestep/state-update/state-hd",
      "Exclusive time %": 5.1e-05,
      "Inclusive time %": 5.1e-05,
      "exclusive_time_rank_avg": 0.000111,
      "exclusive_time_rank_max": 0.000139,
      "exclusive_time_rank_min": 0.000103,
      "inclusive_time_rank_avg": 0.000111,
      "inclusive_time_rank_max": 0.000139,
      "inclusive_time_rank_min": 0.000103
    },
    {
      "path": "main/simulation/timestep/deliver-events/net-buf-receive-DetGABAAB",
      "Exclusive time %": 0.004724,
      "Inclusive time %": 0.004724,
      "exclusive_time_rank_avg": 0.010369,
      "exclusive_time_rank_max": 0.010985,
      "exclusive_time_rank_min": 0.010039,
      "inclusive_time_rank_avg": 0.010369,
      "inclusive_time_rank_max": 0.010985,
      "inclusive_time_rank_min": 0.010039
    }
  ],
  "neurodamus_version": "neurodamus-hippocampus/1.5.0.20211008-3.3.2",
  "backend": "gpu-nmodl-asynchronous",
  "coreneuron_input": "/gpfs/bbp.cscs.ch/project/proj16/NEURONFrontiers2021/hippocampus/generate_coreneuron_input/2733632/output/sim.conf",
  "output_directory": "/gpfs/bbp.cscs.ch/home/magkanar/proj16scratch/FRONTIERS/neuron-frontiers-2021/hippocampus/run_coreneuron_simulation/165892-gpu-nmodl-asynchronous",
  "gpus_per_node": "2",
  "env": {
    "SLURM_CLUSTER_NAME": "ps",
    "SLURM_CONF": "/etc/slurm/slurm.conf",
    "SLURM_CPUS_ON_NODE": "80",
    "SLURM_CPUS_PER_TASK": "2",
    "SLURM_GPUS_ON_NODE": "4",
    "SLURM_GTIDS": "0",
    "SLURM_JOBID": "165892",
    "SLURM_JOB_ACCOUNT": "proj16",
    "SLURM_JOB_CPUS_PER_NODE": "80(x2)",
    "SLURM_JOB_GID": "10067",
    "SLURM_JOB_GPUS": "0,1,2,3",
    "SLURM_JOB_ID": "165892",
    "SLURM_JOB_NAME": "run_coreneuron_gpu_sim.sh",
    "SLURM_JOB_NODELIST": "ldir01u[05,09]",
    "SLURM_JOB_NUM_NODES": "2",
    "SLURM_JOB_PARTITION": "prod",
    "SLURM_JOB_QOS": "normal",
    "SLURM_JOB_UID": "195996",
    "SLURM_JOB_USER": "magkanar",
    "SLURM_KILL_BAD_EXIT": "1",
    "SLURM_LOCALID": "0",
    "SLURM_MEM_PER_NODE": "756000",
    "SLURM_NNODES": "2",
    "SLURM_NODEID": "0",
    "SLURM_NODELIST": "ldir01u[05,09]",
    "SLURM_NODE_ALIASES": "(null)",
    "SLURM_NPROCS": "80",
    "SLURM_NTASKS": "80",
    "SLURM_PRIO_PROCESS": "0",
    "SLURM_PROCID": "0",
    "SLURM_SPANK_AUKS": "no",
    "SLURM_SUBMIT_DIR": "/gpfs/bbp.cscs.ch/data/scratch/proj16/magkanar/FRONTIERS/neuron-frontiers-2021/hippocampus/run_coreneuron_simulation",
    "SLURM_SUBMIT_HOST": "bbpv1.epfl.ch",
    "SLURM_TASKS_PER_NODE": "40(x2)",
    "SLURM_TASK_PID": "28750",
    "SLURM_TIME_FORMAT": "relative",
    "SLURM_TOPOLOGY_ADDR": "ibsw69.ibsw50.ibsw9.ldir01u05",
    "SLURM_TOPOLOGY_ADDR_PATTERN": "switch.switch.switch.node",
    "SLURM_WORKING_CLUSTER": "ps:bbpv1:6810:9472:101",
    "NVCOMPILER_ACC_SYNCHRONOUS": "0",
    "CALI_CHANNEL_FLUSH_ON_EXIT": "false",
    "CALI_MPIREPORT_CONFIG": "SELECT annotation, mpi.function, min(sum#sum#time.duration) as \"exclusive_time_rank_min\", max(sum#sum#time.duration) as \"exclusive_time_rank_max\", avg(sum#sum#time.duration) as \"exclusive_time_rank_avg\", min(inclusive#sum#time.duration) AS \"inclusive_time_rank_min\", max(inclusive#sum#time.duration) AS \"inclusive_time_rank_max\", avg(inclusive#sum#time.duration) AS \"inclusive_time_rank_avg\", percent_total(sum#sum#time.duration) AS \"Exclusive time %\", inclusive_percent_total(sum#sum#time.duration) AS \"Inclusive time %\" GROUP BY prop:nested FORMAT json",
    "CALI_MPIREPORT_FILENAME": "caliper.json",
    "CALI_MPIREPORT_LOCAL_CONFIG": "SELECT sum(sum#time.duration), inclusive_sum(sum#time.duration) GROUP BY prop:nested",
    "CALI_MPI_BLACKLIST": "MPI_Comm_rank,MPI_Comm_size,MPI_Wtick,MPI_Wtime",
    "CALI_SERVICES_ENABLE": "aggregate,event,mpi,mpireport,nvtx,timestamp"
  }
}
